Workbook

Sheet Monthly
A1: US macro and market monthly trend table, Jan 2018 - Sep 2026
A2: Blue = data from feeds (sources in header comments). Black = formulas. Yellow fill = sparse anchor value, not from a feed (see Anchors sheet). Grey = quarterly series held across the quarter.
A4: Month | B4: S&P 500 (monthly avg) | C4: S&P 500 y/y | D4: 10y Treasury yield (%) | E4: 1y Treasury yield (%) | F4: Fed funds effective (%) | G4: Curve 10y-1y (pp) | H4: CPI index (NSA) | I4: CPI inflation y/y | J4: Unemployment rate (%) | K4: Sahm rule (pp) | L4: Nominal GDP ($bn SAAR, qtr) | M4: Nominal GDP y/y | N4: Federal debt (% GDP, qtr) | O4: Federal interest paid ($bn SAAR, qtr) | P4: Interest paid (% GDP) | Q4: M2 ($bn) | R4: M2 y/y | S4: Fed balance sheet ($trn) | T4: Industrial production (index) | U4: Industrial production y/y | V4: Retail sales ($mn) | W4: Retail sales y/y | X4: Nominal PCE ($bn SAAR) | Y4: Nominal PCE y/y | Z4: Real disposable income ($bn 2017) | AA4: Real disposable income y/y | AB4: Case-Shiller national HPI (SA) | AC4: House prices y/y | AD4: Brent ($/bbl, monthly avg) | AE4: WTI ($/bbl, monthly avg) | AF4: Gold ($/oz, monthly) | AG4: Gold y/y | AH4: VIX (monthly close) | AI4: EUR/USD (monthly avg) | AJ4: 2y Treasury yield (%)
A5: 43101 | B5: 2789.8 | D5: 2.58 | E5: 1.8029 | F5: 1.41 | G5: =IF(OR(D5="",E5=""),"",D5-E5) -> 0.7771 | H5: 247.867 | J5: 4 | K5: -0.07 | L5: 20328.553 | N5: 103.7439 | O5: 507.619 | P5: =IF(OR(O5="",L5="",L5=0),"",O5/L5) -> 0.024970739 | Q5: 13902.4 | S5: 4.4379 | T5: 101.4625 | V5: 481190 | X5: 13703.3 | Z5: 14886.6 | AB5: 196.08 | AD5: 69.08 | AE5: 63.6986 | AF5: 1331 | AH5: 13.54 | AI5: 1.2197 | AJ5: 2.38
A6: 43132 | B6: 2705.16 | D6: 2.86 | E6: 1.9637 | F6: 1.42 | G6: =IF(OR(D6="",E6=""),"",D6-E6) -> 0.8963 | H6: 248.991 | J6: 4.1 | K6: -0.03 | L6: 20328.553 | N6: 103.7439 | O6: 507.619 | P6: =IF(OR(O6="",L6="",L6=0),"",O6/L6) -> 0.024970739 | Q6: 13949.8 | S6: 4.4152 | T6: 101.7085 | V6: 484223 | X6: 13738.7 | Z6: 14921.1 | AB6: 196.871 | AD6: 65.32 | AE6: 62.2295 | AF6: 1331 | AH6: 19.85 | AI6: 1.234 | AJ6: 2.61
A7: 43160 | B7: 2702.77 | D7: 2.84 | E7: 2.0629 | F7: 1.51 | G7: =IF(OR(D7="",E7=""),"",D7-E7) -> 0.7771 | H7: 249.554 | J7: 4 | K7: -0.03 | L7: 20328.553 | N7: 103.7439 | O7: 507.619 | P7: =IF(OR(O7="",L7="",L7=0),"",O7/L7) -> 0.024970739 | Q7: 14014.5 | S7: 4.3992 | T7: 102.2067 | V7: 484447 | X7: 13793.2 | Z7: 14974.8 | AB7: 198.537 | AD7: 66.02 | AE7: 62.7248 | AF7: 1325 | AH7: 19.97 | AI7: 1.2334 | AJ7: 2.81
A8: 43191 | B8: 2653.63 | D8: 2.87 | E8: 2.1538 | F8: 1.69 | G8: =IF(OR(D8="",E8=""),"",D8-E8) -> 0.7162 | H8: 250.546 | J8: 4 | K8: 0 | L8: 20580.912 | N8: 102.9841 | O8: 531.778 | P8: =IF(OR(O8="",L8="",L8=0),"",O8/L8) -> 0.025838408 | Q8: 14034.8 | S8: 4.3821 | T8: 103.3329 | V8: 484252 | X8: 13838.4 | Z8: 15007.2 | AB8: 200.576 | AD8: 72.11 | AE8: 66.2538 | AF8: 1335 | AH8: 15.93 | AI8: 1.227 | AJ8: 2.88
A9: 43221 | B9: 2701.49 | D9: 2.98 | E9: 2.2736 | F9: 1.7 | G9: =IF(OR(D9="",E9=""),"",D9-E9) -> 0.7064 | H9: 251.588 | J9: 3.8 | K9: -0.1 | L9: 20580.912 | N9: 102.9841 | O9: 531.778 | P9: =IF(OR(O9="",L9="",L9=0),"",O9/L9) -> 0.025838408 | Q9: 14091 | S9: 4.3434 | T9: 102.4024 | V9: 492202 | X9: 13905 | Z9: 15057.8 | AB9: 202.413 | AD9: 76.98 | AE9: 69.9782 | AF9: 1303 | AH9: 15.43 | AI9: 1.1823 | AJ9: 2.95
A10: 43252 | B10: 2754.35 | D10: 2.91 | E10: 2.3281 | F10: 1.82 | G10: =IF(OR(D10="",E10=""),"",D10-E10) -> 0.5819 | H10: 251.989 | J10: 4 | K10: 0 | L10: 20580.912 | N10: 102.9841 | O10: 531.778 | P10: =IF(OR(O10="",L10="",L10=0),"",O10/L10) -> 0.025838408 | Q10: 14133.2 | S10: 4.3164 | T10: 103.198 | V10: 490468 | X10: 13930.4 | Z10: 15119.3 | AB10: 204.005 | AD10: 74.41 | AE10: 67.8733 | AF10: 1282 | AH10: 16.09 | AI10: 1.1679 | AJ10: 3.02
A11: 43282 | B11: 2793.64 | D11: 2.89 | E11: 2.3876 | F11: 1.91 | G11: =IF(OR(D11="",E11=""),"",D11-E11) -> 0.5024 | H11: 252.006 | J11: 3.8 | K11: -0.07 | L11: 20798.73 | N11: 103.4489 | O11: 551.891 | P11: =IF(OR(O11="",L11="",L11=0),"",O11/L11) -> 0.026534841 | Q11: 14170 | S11: 4.2876 | T11: 103.3646 | V11: 493382 | X11: 13974.8 | Z11: 15184.7 | AB11: 204.914 | AD11: 74.25 | AE11: 70.9814 | AF11: 1238 | AH11: 12.83 | AI11: 1.1685 | AJ11: 3.1
A12: 43313 | B12: 2857.82 | D12: 2.89 | E12: 2.4457 | F12: 1.91 | G12: =IF(OR(D12="",E12=""),"",D12-E12) -> 0.4443 | H12: 252.146 | J12: 3.8 | K12: 0 | L12: 20798.73 | N12: 103.4489 | O12: 551.891 | P12: =IF(OR(O12="",L12="",L12=0),"",O12/L12) -> 0.026534841 | Q12: 14221.3 | S12: 4.2381 | T12: 104.0327 | V12: 493757 | X12: 14014 | Z12: 15238.6 | AB12: 205.292 | AD12: 72.53 | AE12: 68.0557 | AF12: 1202 | AH12: 12.86 | AI12: 1.1547 | AJ12: 3.06
A13: 43344 | B13: 2901.5 | D13: 3 | E13: 2.5579 | F13: 1.95 | G13: =IF(OR(D13="",E13=""),"",D13-E13) -> 0.4421 | H13: 252.439 | J13: 3.7 | K13: -0.1 | L13: 20798.73 | N13: 103.4489 | O13: 551.891 | P13: =IF(OR(O13="",L13="",L13=0),"",O13/L13) -> 0.026534841 | Q13: 14243.9 | S13: 4.2051 | T13: 104.1004 | V13: 491744 | X13: 14017.8 | Z13: 15237.5 | AB13: 205.339 | AD13: 78.89 | AE13: 70.2321 | AF13: 1198 | AH13: 12.12 | AI13: 1.1667 | AJ13: 3.16
A14: 43374 | B14: 2785.46 | D14: 3.15 | E14: 2.6518 | F14: 2.19 | G14: =IF(OR(D14="",E14=""),"",D14-E14) -> 0.4982 | H14: 252.885 | J14: 3.8 | K14: 0 | L14: 20917.867 | N14: 105.0494 | O14: 571.229 | P14: =IF(OR(O14="",L14="",L14=0),"",O14/L14) -> 0.027308186 | Q14: 14257.6 | S14: 4.168 | T14: 103.9856 | V14: 496568 | X14: 14083.1 | Z14: 15274.1 | AB14: 205.336 | AD14: 81.03 | AE14: 70.7487 | AF14: 1215 | AH14: 21.23 | AI14: 1.1488 | AJ14: 3.27
A15: 43405 | B15: 2723.23 | D15: 3.12 | E15: 2.6985 | F15: 2.2 | G15: =IF(OR(D15="",E15=""),"",D15-E15) -> 0.4215 | H15: 252.038 | J15: 3.8 | K15: 0 | L15: 20917.867 | N15: 105.0494 | O15: 571.229 | P15: =IF(OR(O15="",L15="",L15=0),"",O15/L15) -> 0.027308186 | Q15: 14288.4 | S15: 4.1228 | T15: 104.0681 | V15: 499451 | X15: 14162.9 | Z15: 15315.2 | AB15: 205.075 | AD15: 64.75 | AE15: 56.9635 | AF15: 1221 | AH15: 18.07 | AI15: 1.1364 | AJ15: 3.36
A16: 43435 | B16: 2567.31 | D16: 2.83 | E16: 2.6553 | F16: 2.27 | G16: =IF(OR(D16="",E16=""),"",D16-E16) -> 0.1747 | H16: 251.233 | J16: 3.9 | K16: 0.07 | L16: 20917.867 | N16: 105.0494 | O16: 571.229 | P16: =IF(OR(O16="",L16="",L16=0),"",O16/L16) -> 0.027308186 | Q16: 14392 | S16: 4.0836 | T16: 104.0936 | V16: 489878 | X16: 14051.6 | Z16: 15506.5 | AB16: 204.664 | AD16: 57.36 | AE16: 49.5228 | AF16: 1250 | AH16: 25.42 | AI16: 1.138 | AJ16: 3.33
A17: 43466 | B17: 2607.39 | C17: =IF(OR(B17="",B5=""),"",B17/B5-1) -> -0.065384615 | D17: 2.71 | E17: 2.5795 | F17: 2.4 | G17: =IF(OR(D17="",E17=""),"",D17-E17) -> 0.1305 | H17: 251.712 | I17: =IF(OR(H17="",H5=""),"",H17/H5-1) -> 0.015512351 | J17: 4 | K17: 0.13 | L17: 21111.6 | M17: =IF(OR(L17="",L5=""),"",L17/L5-1) -> 0.038519564 | N17: 104.3402 | O17: 579.714 | P17: =IF(OR(O17="",L17="",L17=0),"",O17/L17) -> 0.027459501 | Q17: 14460.2 | R17: =IF(OR(Q17="",Q5=""),"",Q17/Q5-1) -> 0.040122569 | S17: 4.0503 | T17: 103.4021 | U17: =IF(OR(T17="",T5=""),"",T17/T5-1) -> 0.019116422 | V17: 490789 | W17: =IF(OR(V17="",V5=""),"",V17/V5-1) -> 0.019948461 | X17: 14084.6 | Y17: =IF(OR(X17="",X5=""),"",X17/X5-1) -> 0.027825414 | Z17: 15536.3 | AA17: =IF(OR(Z17="",Z5=""),"",Z17/Z5-1) -> 0.043643277 | AB17: 204.165 | AC17: =IF(OR(AB17="",AB5=""),"",AB17/AB5-1) -> 0.04123317 | AD17: 59.41 | AE17: 51.3757 | AF17: 1292 | AG17: =IF(OR(AF17="",AF5=""),"",AF17/AF5-1) -> -0.029301277 | AH17: 16.57 | AI17: 1.1418 | AJ17: 3.16
A18: 43497 | B18: 2754.86 | C18: =IF(OR(B18="",B6=""),"",B18/B6-1) -> 0.018372296 | D18: 2.68 | E18: 2.5495 | F18: 2.4 | G18: =IF(OR(D18="",E18=""),"",D18-E18) -> 0.1305 | H18: 252.776 | I18: =IF(OR(H18="",H6=""),"",H18/H6-1) -> 0.015201353 | J18: 3.8 | K18: 0.13 | L18: 21111.6 | M18: =IF(OR(L18="",L6=""),"",L18/L6-1) -> 0.038519564 | N18: 104.3402 | O18: 579.714 | P18: =IF(OR(O18="",L18="",L18=0),"",O18/L18) -> 0.027459501 | Q18: 14506.6 | R18: =IF(OR(Q18="",Q6=""),"",Q18/Q6-1) -> 0.039914551 | S18: 4.0027 | T18: 102.8371 | U18: =IF(OR(T18="",T6=""),"",T18/T6-1) -> 0.011096418 | V18: 492328 | W18: =IF(OR(V18="",V6=""),"",V18/V6-1) -> 0.016738156 | X18: 14117.4 | Y18: =IF(OR(X18="",X6=""),"",X18/X6-1) -> 0.027564471 | Z18: 15560.4 | AA18: =IF(OR(Z18="",Z6=""),"",Z18/Z6-1) -> 0.042845367 | AB18: 204.389 | AC18: =IF(OR(AB18="",AB6=""),"",AB18/AB6-1) -> 0.038187443 | AD18: 63.96 | AE18: 54.9547 | AF18: 1320 | AG18: =IF(OR(AF18="",AF6=""),"",AF18/AF6-1) -> -0.0082644628 | AH18: 14.78 | AI18: 1.1349 | AJ18: 3
A19: 43525 | B19: 2803.98 | C19: =IF(OR(B19="",B7=""),"",B19/B7-1) -> 0.037446768 | D19: 2.57 | E19: 2.491 | F19: 2.41 | G19: =IF(OR(D19="",E19=""),"",D19-E19) -> 0.079 | H19: 254.202 | I19: =IF(OR(H19="",H7=""),"",H19/H7-1) -> 0.018625227 | J19: 3.8 | K19: 0.1 | L19: 21111.6 | M19: =IF(OR(L19="",L7=""),"",L19/L7-1) -> 0.038519564 | N19: 104.3402 | O19: 579.714 | P19: =IF(OR(O19="",L19="",L19=0),"",O19/L19) -> 0.027459501 | Q19: 14559.5 | R19: =IF(OR(Q19="",Q7=""),"",Q19/Q7-1) -> 0.038888294 | S19: 3.9648 | T19: 102.8757 | U19: =IF(OR(T19="",T7=""),"",T19/T7-1) -> 0.0065455591 | V19: 499614 | W19: =IF(OR(V19="",V7=""),"",V19/V7-1) -> 0.031307862 | X19: 14248.6 | Y19: =IF(OR(X19="",X7=""),"",X19/X7-1) -> 0.033016269 | Z19: 15566.5 | AA19: =IF(OR(Z19="",Z7=""),"",Z19/Z7-1) -> 0.039513049 | AB19: 205.735 | AC19: =IF(OR(AB19="",AB7=""),"",AB19/AB7-1) -> 0.036255207 | AD19: 66.14 | AE19: 58.1514 | AF19: 1301 | AG19: =IF(OR(AF19="",AF7=""),"",AF19/AF7-1) -> -0.018113208 | AH19: 13.71 | AI19: 1.1296 | AJ19: 2.84
A20: 43556 | B20: 2903.8 | C20: =IF(OR(B20="",B8=""),"",B20/B8-1) -> 0.094274635 | D20: 2.53 | E20: 2.4248 | F20: 2.42 | G20: =IF(OR(D20="",E20=""),"",D20-E20) -> 0.1052 | H20: 255.548 | I20: =IF(OR(H20="",H8=""),"",H20/H8-1) -> 0.019964398 | J20: 3.7 | K20: 0 | L20: 21397.938 | M20: =IF(OR(L20="",L8=""),"",L20/L8-1) -> 0.039698241 | N20: 102.9224 | O20: 586.409 | P20: =IF(OR(O20="",L20="",L20=0),"",O20/L20) -> 0.02740493 | Q20: 14594 | R20: =IF(OR(Q20="",Q8=""),"",Q20/Q8-1) -> 0.039843817 | S20: 3.9331 | T20: 102.274 | U20: =IF(OR(T20="",T8=""),"",T20/T8-1) -> -0.010247462 | V20: 499609 | W20: =IF(OR(V20="",V8=""),"",V20/V8-1) -> 0.031712827 | X20: 14290 | Y20: =IF(OR(X20="",X8=""),"",X20/X8-1) -> 0.032633831 | Z20: 15534.2 | AA20: =IF(OR(Z20="",Z8=""),"",Z20/Z8-1) -> 0.035116477 | AB20: 207.649 | AC20: =IF(OR(AB20="",AB8=""),"",AB20/AB8-1) -> 0.035263441 | AD20: 71.23 | AE20: 63.8624 | AF20: 1286 | AG20: =IF(OR(AF20="",AF8=""),"",AF20/AF8-1) -> -0.03670412 | AH20: 13.12 | AI20: 1.1234 | AJ20: 2.77
A21: 43586 | B21: 2854.71 | C21: =IF(OR(B21="",B9=""),"",B21/B9-1) -> 0.056716849 | D21: 2.4 | E21: 2.3405 | F21: 2.39 | G21: =IF(OR(D21="",E21=""),"",D21-E21) -> 0.0595 | H21: 256.092 | I21: =IF(OR(H21="",H9=""),"",H21/H9-1) -> 0.017902285 | J21: 3.6 | K21: -0.07 | L21: 21397.938 | M21: =IF(OR(L21="",L9=""),"",L21/L9-1) -> 0.039698241 | N21: 102.9224 | O21: 586.409 | P21: =IF(OR(O21="",L21="",L21=0),"",O21/L21) -> 0.02740493 | Q21: 14703.2 | R21: =IF(OR(Q21="",Q9=""),"",Q21/Q9-1) -> 0.043446171 | S21: 3.8717 | T21: 102.392 | U21: =IF(OR(T21="",T9=""),"",T21/T9-1) -> -0.00010156012 | V21: 505356 | W21: =IF(OR(V21="",V9=""),"",V21/V9-1) -> 0.0267248 | X21: 14353.3 | Y21: =IF(OR(X21="",X9=""),"",X21/X9-1) -> 0.032240201 | Z21: 15532.4 | AA21: =IF(OR(Z21="",Z9=""),"",Z21/Z9-1) -> 0.031518549 | AB21: 209.312 | AC21: =IF(OR(AB21="",AB9=""),"",AB21/AB9-1) -> 0.034083779 | AD21: 71.32 | AE21: 60.8268 | AF21: 1284 | AG21: =IF(OR(AF21="",AF9=""),"",AF21/AF9-1) -> -0.014581734 | AH21: 18.71 | AI21: 1.1187 | AJ21: 2.68
A22: 43617 | B22: 2890.17 | C22: =IF(OR(B22="",B10=""),"",B22/B10-1) -> 0.04931109 | D22: 2.07 | E22: 1.995 | F22: 2.38 | G22: =IF(OR(D22="",E22=""),"",D22-E22) -> 0.075 | H22: 256.143 | I22: =IF(OR(H22="",H10=""),"",H22/H10-1) -> 0.016484847 | J22: 3.6 | K22: -0.07 | L22: 21397.938 | M22: =IF(OR(L22="",L10=""),"",L22/L10-1) -> 0.039698241 | N22: 102.9224 | O22: 586.409 | P22: =IF(OR(O22="",L22="",L22=0),"",O22/L22) -> 0.02740493 | Q22: 14798.8 | R22: =IF(OR(Q22="",Q10=""),"",Q22/Q10-1) -> 0.047094784 | S22: 3.8421 | T22: 102.4375 | U22: =IF(OR(T22="",T10=""),"",T22/T10-1) -> -0.0073693289 | V22: 505681 | W22: =IF(OR(V22="",V10=""),"",V22/V10-1) -> 0.031017314 | X22: 14408.7 | Y22: =IF(OR(X22="",X10=""),"",X22/X10-1) -> 0.03433498 | Z22: 15562.1 | AA22: =IF(OR(Z22="",Z10=""),"",Z22/Z10-1) -> 0.02928707 | AB22: 210.548 | AC22: =IF(OR(AB22="",AB10=""),"",AB22/AB10-1) -> 0.032072743 | AD22: 64.22 | AE22: 54.6575 | AF22: 1359 | AG22: =IF(OR(AF22="",AF10=""),"",AF22/AF10-1) -> 0.060062402 | AH22: 15.08 | AI22: 1.1295 | AJ22: 2.36
A23: 43647 | B23: 2996.1136 | C23: =IF(OR(B23="",B11=""),"",B23/B11-1) -> 0.072476625 | D23: 2.06 | E23: 1.9623 | F23: 2.4 | G23: =IF(OR(D23="",E23=""),"",D23-E23) -> 0.0977 | H23: 256.571 | I23: =IF(OR(H23="",H11=""),"",H23/H11-1) -> 0.018114648 | J23: 3.7 | K23: 0 | L23: 21717.171 | M23: =IF(OR(L23="",L11=""),"",L23/L11-1) -> 0.044158514 | N23: 104.6149 | O23: 578.256 | P23: =IF(OR(O23="",L23="",L23=0),"",O23/L23) -> 0.026626673 | Q23: 14882.7 | R23: =IF(OR(Q23="",Q11=""),"",Q23/Q11-1) -> 0.050296401 | S23: 3.8038 | T23: 101.9408 | U23: =IF(OR(T23="",T11=""),"",T23/T11-1) -> -0.013774542 | V23: 509389 | W23: =IF(OR(V23="",V11=""),"",V23/V11-1) -> 0.032443421 | X23: 14496 | Y23: =IF(OR(X23="",X11=""),"",X23/X11-1) -> 0.037295704 | Z23: 15581.4 | AA23: =IF(OR(Z23="",Z11=""),"",Z23/Z11-1) -> 0.026124981 | AB23: 211.298 | AC23: =IF(OR(AB23="",AB11=""),"",AB23/AB11-1) -> 0.031154533 | AD23: 63.92 | AE23: 57.3581 | AF23: 1413 | AG23: =IF(OR(AF23="",AF11=""),"",AF23/AF11-1) -> 0.14135703 | AH23: 16.12 | AI23: 1.1211 | AJ23: 2.31
A24: 43678 | B24: 2897.4982 | C24: =IF(OR(B24="",B12=""),"",B24/B12-1) -> 0.013884079 | D24: 1.63 | E24: 1.7723 | F24: 2.13 | G24: =IF(OR(D24="",E24=""),"",D24-E24) -> -0.1423 | H24: 256.558 | I24: =IF(OR(H24="",H12=""),"",H24/H12-1) -> 0.017497799 | J24: 3.6 | K24: 0 | L24: 21717.171 | M24: =IF(OR(L24="",L12=""),"",L24/L12-1) -> 0.044158514 | N24: 104.6149 | O24: 578.256 | P24: =IF(OR(O24="",L24="",L24=0),"",O24/L24) -> 0.026626673 | Q24: 14974.4 | R24: =IF(OR(Q24="",Q12=""),"",Q24/Q12-1) -> 0.052955778 | S24: 3.7731 | T24: 102.639 | U24: =IF(OR(T24="",T12=""),"",T24/T12-1) -> -0.013396749 | V24: 513222 | W24: =IF(OR(V24="",V12=""),"",V24/V12-1) -> 0.039422226 | X24: 14558.2 | Y24: =IF(OR(X24="",X12=""),"",X24/X12-1) -> 0.038832596 | Z24: 15664.3 | AA24: =IF(OR(Z24="",Z12=""),"",Z24/Z12-1) -> 0.027935637 | AB24: 211.656 | AC24: =IF(OR(AB24="",AB12=""),"",AB24/AB12-1) -> 0.030999747 | AD24: 59.04 | AE24: 54.8059 | AF24: 1500 | AG24: =IF(OR(AF24="",AF12=""),"",AF24/AF12-1) -> 0.24792013 | AH24: 18.98 | AI24: 1.1129 | AJ24: 2.08
A25: 43709 | B25: 2982.156 | C25: =IF(OR(B25="",B13=""),"",B25/B13-1) -> 0.027798035 | D25: 1.7 | E25: 1.796 | F25: 2.04 | G25: =IF(OR(D25="",E25=""),"",D25-E25) -> -0.096 | H25: 256.759 | I25: =IF(OR(H25="",H13=""),"",H25/H13-1) -> 0.017113045 | J25: 3.5 | K25: -0.03 | L25: 21717.171 | M25: =IF(OR(L25="",L13=""),"",L25/L13-1) -> 0.044158514 | N25: 104.6149 | O25: 578.256 | P25: =IF(OR(O25="",L25="",L25=0),"",O25/L25) -> 0.026626673 | Q25: 15047.2 | R25: =IF(OR(Q25="",Q13=""),"",Q25/Q13-1) -> 0.056396071 | S25: 3.8084 | T25: 102.2917 | U25: =IF(OR(T25="",T13=""),"",T25/T13-1) -> -0.017374573 | V25: 509503 | W25: =IF(OR(V25="",V13=""),"",V25/V13-1) -> 0.03611432 | X25: 14590.6 | Y25: =IF(OR(X25="",X13=""),"",X25/X13-1) -> 0.040862332 | Z25: 15697.5 | AA25: =IF(OR(Z25="",Z13=""),"",Z25/Z13-1) -> 0.030188679 | AB25: 211.834 | AC25: =IF(OR(AB25="",AB13=""),"",AB25/AB13-1) -> 0.031630621 | AD25: 62.83 | AE25: 56.947 | AF25: 1511 | AG25: =IF(OR(AF25="",AF13=""),"",AF25/AF13-1) -> 0.26126878 | AH25: 16.24 | AI25: 1.1011 | AJ25: 2.11
A26: 43739 | B26: 2977.68 | C26: =IF(OR(B26="",B14=""),"",B26/B14-1) -> 0.069008351 | D26: 1.71 | E26: 1.6082 | F26: 1.83 | G26: =IF(OR(D26="",E26=""),"",D26-E26) -> 0.1018 | H26: 257.346 | I26: =IF(OR(H26="",H14=""),"",H26/H14-1) -> 0.017640429 | J26: 3.6 | K26: -0.03 | L26: 21933.217 | M26: =IF(OR(L26="",L14=""),"",L26/L14-1) -> 0.048539844 | N26: 105.7819 | O26: 564.241 | P26: =IF(OR(O26="",L26="",L26=0),"",O26/L26) -> 0.02572541 | Q26: 15185.6 | R26: =IF(OR(Q26="",Q14=""),"",Q26/Q14-1) -> 0.065088093 | S26: 3.9702 | T26: 101.4281 | U26: =IF(OR(T26="",T14=""),"",T26/T14-1) -> -0.024594752 | V26: 510902 | W26: =IF(OR(V26="",V14=""),"",V26/V14-1) -> 0.028866137 | X26: 14617.4 | Y26: =IF(OR(X26="",X14=""),"",X26/X14-1) -> 0.03793909 | Z26: 15718.1 | AA26: =IF(OR(Z26="",Z14=""),"",Z26/Z14-1) -> 0.029068816 | AB26: 211.926 | AC26: =IF(OR(AB26="",AB14=""),"",AB26/AB14-1) -> 0.032093739 | AD26: 59.71 | AE26: 53.963 | AF26: 1495 | AG26: =IF(OR(AF26="",AF14=""),"",AF26/AF14-1) -> 0.23045267 | AH26: 13.22 | AI26: 1.1058 | AJ26: 1.97
A27: 43770 | B27: 3104.9045 | C27: =IF(OR(B27="",B15=""),"",B27/B15-1) -> 0.14015507 | D27: 1.81 | E27: 1.5679 | F27: 1.55 | G27: =IF(OR(D27="",E27=""),"",D27-E27) -> 0.2421 | H27: 257.208 | I27: =IF(OR(H27="",H15=""),"",H27/H15-1) -> 0.02051278 | J27: 3.6 | K27: 0 | L27: 21933.217 | M27: =IF(OR(L27="",L15=""),"",L27/L15-1) -> 0.048539844 | N27: 105.7819 | O27: 564.241 | P27: =IF(OR(O27="",L27="",L27=0),"",O27/L27) -> 0.02572541 | Q27: 15301.3 | R27: =IF(OR(Q27="",Q15=""),"",Q27/Q15-1) -> 0.070889673 | S27: 4.0426 | T27: 101.9372 | U27: =IF(OR(T27="",T15=""),"",T27/T15-1) -> -0.020476015 | V27: 514649 | W27: =IF(OR(V27="",V15=""),"",V27/V15-1) -> 0.030429411 | X27: 14711 | Y27: =IF(OR(X27="",X15=""),"",X27/X15-1) -> 0.038699701 | Z27: 15766.9 | AA27: =IF(OR(Z27="",Z15=""),"",Z27/Z15-1) -> 0.029493575 | AB27: 212.063 | AC27: =IF(OR(AB27="",AB15=""),"",AB27/AB15-1) -> 0.034075338 | AD27: 63.21 | AE27: 57.0489 | AF27: 1471 | AG27: =IF(OR(AF27="",AF15=""),"",AF27/AF15-1) -> 0.2047502 | AH27: 12.62 | AI27: 1.1051 | AJ27: 2.01
A28: 43800 | B28: 3176.7495 | C28: =IF(OR(B28="",B16=""),"",B28/B16-1) -> 0.23738446 | D28: 1.86 | E28: 1.549 | F28: 1.55 | G28: =IF(OR(D28="",E28=""),"",D28-E28) -> 0.311 | H28: 256.974 | I28: =IF(OR(H28="",H16=""),"",H28/H16-1) -> 0.022851297 | J28: 3.6 | K28: 0.03 | L28: 21933.217 | M28: =IF(OR(L28="",L16=""),"",L28/L16-1) -> 0.048539844 | N28: 105.7819 | O28: 564.241 | P28: =IF(OR(O28="",L28="",L28=0),"",O28/L28) -> 0.02572541 | Q28: 15351.5 | R28: =IF(OR(Q28="",Q16=""),"",Q28/Q16-1) -> 0.066668983 | S28: 4.116 | T28: 101.7003 | U28: =IF(OR(T28="",T16=""),"",T28/T16-1) -> -0.022991807 | V28: 516273 | W28: =IF(OR(V28="",V16=""),"",V28/V16-1) -> 0.053880762 | X28: 14774.8 | Y28: =IF(OR(X28="",X16=""),"",X28/X16-1) -> 0.051467449 | Z28: 15683.8 | AA28: =IF(OR(Z28="",Z16=""),"",Z28/Z16-1) -> 0.011433915 | AB28: 212.194 | AC28: =IF(OR(AB28="",AB16=""),"",AB28/AB16-1) -> 0.03679201 | AD28: 67.31 | AE28: 59.8167 | AF28: 1479 | AG28: =IF(OR(AF28="",AF16=""),"",AF28/AF16-1) -> 0.1832 | AH28: 13.78 | AI28: 1.1114 | AJ28: 1.99
... A78: 45323 | B78: 5011.96 | C78: =IF(OR(B78="",B66=""),"",B78/B66-1) -> 0.22851651 | D78: 4.21 | E78: 4.9225 | F78: 5.33 | G78: =IF(OR(D78="",E78=""),"",D78-E78) -> -0.7125 | H78: 310.326 | I78: =IF(OR(H78="",H66=""),"",H78/H66-1) -> 0.031531711 | J78: 3.9 | K78: 0.3 | L78: 28793.191 | M78: =IF(OR(L78="",L66=""),"",L78/L66-1) -> 0.056969015 | N78: 120.4763 | O78: 1062.76 | P78: =IF(OR(O78="",L78="",L78=0),"",O78/L78) -> 0.036910115 | Q78: 20921.7 | R78: =IF(OR(Q78="",Q66=""),"",Q78/Q66-1) -> -0.014995151 | S78: 7.6037 | T78: 100.285 | U78: =IF(OR(T78="",T66=""),"",T78/T66-1) -> -0.0035432664 | V78: 664621 | W78: =IF(OR(V78="",V66=""),"",V78/V66-1) -> -0.00010681639 | X78: 19373.5 | Y78: =IF(OR(X78="",X66=""),"",X78/X66-1) -> 0.05050401 | Z78: 17681 | AA78: =IF(OR(Z78="",Z66=""),"",Z78/Z66-1) -> 0.039820277 | AB78: 312.625 | AC78: =IF(OR(AB78="",AB66=""),"",AB78/AB66-1) -> 0.065299766 | AD78: 83.48 | AE78: 77.249 | AF78: 2023 | AG78: =IF(OR(AF78="",AF66=""),"",AF78/AF66-1) -> 0.090566038 | AH78: 13.4 | AI78: 1.0793 | AJ78: 4.99
A79: 45352 | B79: 5170.57 | C79: =IF(OR(B79="",B67=""),"",B79/B67-1) -> 0.30288346 | D79: 4.21 | E79: 4.9925 | F79: 5.33 | G79: =IF(OR(D79="",E79=""),"",D79-E79) -> -0.7825 | H79: 312.332 | I79: =IF(OR(H79="",H67=""),"",H79/H67-1) -> 0.034773851 | J79: 3.9 | K79: 0.33 | L79: 28793.191 | M79: =IF(OR(L79="",L67=""),"",L79/L67-1) -> 0.056969015 | N79: 120.4763 | O79: 1062.76 | P79: =IF(OR(O79="",L79="",L79=0),"",O79/L79) -> 0.036910115 | Q79: 20965.9 | R79: =IF(OR(Q79="",Q67=""),"",Q79/Q67-1) -> 0.0011269058 | S79: 7.52 | T79: 100.4575 | U79: =IF(OR(T79="",T67=""),"",T79/T67-1) -> -0.0055731262 | V79: 664328 | W79: =IF(OR(V79="",V67=""),"",V79/V67-1) -> 0.014015197 | X79: 19513.7 | Y79: =IF(OR(X79="",X67=""),"",X79/X67-1) -> 0.055724774 | Z79: 17699.2 | AA79: =IF(OR(Z79="",Z67=""),"",Z79/Z67-1) -> 0.035476926 | AB79: 316.808 | AC79: =IF(OR(AB79="",AB67=""),"",AB79/AB67-1) -> 0.065319806 | AD79: 85.41 | AE79: 81.278 | AF79: 2158 | AG79: =IF(OR(AF79="",AF67=""),"",AF79/AF67-1) -> 0.12807109 | AH79: 13.01 | AI79: 1.087
A80: 45383 | B80: 5112.49 | C80: =IF(OR(B80="",B68=""),"",B80/B68-1) -> 0.24045382 | D80: 4.54 | E80: 5.135 | F80: 5.33 | G80: =IF(OR(D80="",E80=""),"",D80-E80) -> -0.595 | H80: 313.548 | I80: =IF(OR(H80="",H68=""),"",H80/H68-1) -> 0.03357364 | J80: 3.9 | K80: 0.4 | L80: 29232.964 | M80: =IF(OR(L80="",L68=""),"",L80/L68-1) -> 0.061707112 | N80: 119.5031 | O80: 1095.97 | P80: =IF(OR(O80="",L80="",L80=0),"",O80/L80) -> 0.037490896 | Q80: 20955.4 | R80: =IF(OR(Q80="",Q68=""),"",Q80/Q68-1) -> 0.0094998603 | S80: 7.4214 | T80: 100.2434 | U80: =IF(OR(T80="",T68=""),"",T80/T68-1) -> -0.0099710626 | V80: 664858 | W80: =IF(OR(V80="",V68=""),"",V80/V68-1) -> 0.0089474052 | X80: 19582.2 | Y80: =IF(OR(X80="",X68=""),"",X80/X68-1) -> 0.054183692 | Z80: 17747.2 | AA80: =IF(OR(Z80="",Z68=""),"",Z80/Z68-1) -> 0.034846294 | AB80: 320.748 | AC80: =IF(OR(AB80="",AB68=""),"",AB80/AB68-1) -> 0.06385491 | AD80: 89.94 | AE80: 85.3473 | AF80: 2331 | AG80: =IF(OR(AF80="",AF68=""),"",AF80/AF68-1) -> 0.1655 | AH80: 15.65 | AI80: 1.0724
A81: 45413 | B81: 5235.23 | C81: =IF(OR(B81="",B69=""),"",B81/B69-1) -> 0.26266553 | D81: 4.48 | E81: 5.1595 | F81: 5.33 | G81: =IF(OR(D81="",E81=""),"",D81-E81) -> -0.6795 | H81: 314.069 | I81: =IF(OR(H81="",H69=""),"",H81/H69-1) -> 0.032690291 | J81: 3.9 | K81: 0.4 | L81: 29232.964 | M81: =IF(OR(L81="",L69=""),"",L81/L69-1) -> 0.061707112 | N81: 119.5031 | O81: 1095.97 | P81: =IF(OR(O81="",L81="",L81=0),"",O81/L81) -> 0.037490896 | Q81: 21021.6 | R81: =IF(OR(Q81="",Q69=""),"",Q81/Q69-1) -> 0.0092273421 | S81: 7.3208 | T81: 100.863 | U81: =IF(OR(T81="",T69=""),"",T81/T69-1) -> -0.00064996443 | V81: 667659 | W81: =IF(OR(V81="",V69=""),"",V81/V69-1) -> 0.008086933 | X81: 19689 | Y81: =IF(OR(X81="",X69=""),"",X81/X69-1) -> 0.058104666 | Z81: 17820.5 | AA81: =IF(OR(Z81="",Z69=""),"",Z81/Z69-1) -> 0.035094649 | AB81: 323.696 | AC81: =IF(OR(AB81="",AB69=""),"",AB81/AB69-1) -> 0.060050629 | AD81: 81.75 | AE81: 80.0245 | AF81: 2351 | AG81: =IF(OR(AF81="",AF69=""),"",AF81/AF69-1) -> 0.18022088 | AH81: 12.92 | AI81: 1.081
A82: 45444 | B82: 5415.14 | C82: =IF(OR(B82="",B70=""),"",B82/B70-1) -> 0.24618534 | D82: 4.31 | E82: 5.1105 | F82: 5.33 | G82: =IF(OR(D82="",E82=""),"",D82-E82) -> -0.8005 | H82: 314.175 | I82: =IF(OR(H82="",H70=""),"",H82/H70-1) -> 0.029713971 | J82: 4.1 | K82: 0.43 | L82: 29232.964 | M82: =IF(OR(L82="",L70=""),"",L82/L70-1) -> 0.061707112 | N82: 119.5031 | O82: 1095.97 | P82: =IF(OR(O82="",L82="",L82=0),"",O82/L82) -> 0.037490896 | Q82: 21070.7 | R82: =IF(OR(Q82="",Q70=""),"",Q82/Q70-1) -> 0.013067999 | S82: 7.2496 | T82: 100.894 | U82: =IF(OR(T82="",T70=""),"",T82/T70-1) -> 0.0077347492 | V82: 666040 | W82: =IF(OR(V82="",V70=""),"",V82/V70-1) -> 0.0023537344 | X82: 19775.3 | Y82: =IF(OR(X82="",X70=""),"",X82/X70-1) -> 0.057909997 | Z82: 17869.8 | AA82: =IF(OR(Z82="",Z70=""),"",Z82/Z70-1) -> 0.03552823 | AB82: 325.256 | AC82: =IF(OR(AB82="",AB70=""),"",AB82/AB70-1) -> 0.054967581 | AD82: 82.25 | AE82: 79.7674 | AF82: 2326 | AG82: =IF(OR(AF82="",AF70=""),"",AF82/AF70-1) -> 0.19711786 | AH82: 12.44 | AI82: 1.0763 | AJ82: 4.71
A83: 45474 | B83: 5538 | C83: =IF(OR(B83="",B71=""),"",B83/B71-1) -> 0.22846212 | D83: 4.25 | E83: 4.8973 | F83: 5.33 | G83: =IF(OR(D83="",E83=""),"",D83-E83) -> -0.6473 | H83: 314.54 | I83: =IF(OR(H83="",H71=""),"",H83/H71-1) -> 0.028947532 | J83: 4.2 | K83: 0.5 | L83: 29568.256 | M83: =IF(OR(L83="",L71=""),"",L83/L71-1) -> 0.053599711 | N83: 120.1717 | O83: 1145.002 | P83: =IF(OR(O83="",L83="",L83=0),"",O83/L83) -> 0.038724029 | Q83: 21098.9 | R83: =IF(OR(Q83="",Q71=""),"",Q83/Q71-1) -> 0.014750724 | S83: 7.2075 | T83: 99.9757 | U83: =IF(OR(T83="",T71=""),"",T83/T71-1) -> -0.0092263447 | V83: 673662 | W83: =IF(OR(V83="",V71=""),"",V83/V71-1) -> 0.015482574 | X83: 19863.6 | Y83: =IF(OR(X83="",X71=""),"",X83/X71-1) -> 0.057046766 | Z83: 17862.8 | AA83: =IF(OR(Z83="",Z71=""),"",Z83/Z71-1) -> 0.032221529 | AB83: 325.566 | AC83: =IF(OR(AB83="",AB71=""),"",AB83/AB71-1) -> 0.049457971 | AD83: 85.15 | AE83: 81.8005 | AF83: 2398 | AG83: =IF(OR(AF83="",AF71=""),"",AF83/AF71-1) -> 0.22911328 | AH83: 16.36 | AI83: 1.0847
A84: 45505 | B84: 5478.21 | C84: =IF(OR(B84="",B72=""),"",B84/B72-1) -> 0.22902606 | D84: 3.87 | E84: 4.4264 | F84: 5.33 | G84: =IF(OR(D84="",E84=""),"",D84-E84) -> -0.5564 | H84: 314.796 | I84: =IF(OR(H84="",H72=""),"",H84/H72-1) -> 0.025307303 | J84: 4.2 | K84: 0.57 | L84: 29568.256 | M84: =IF(OR(L84="",L72=""),"",L84/L72-1) -> 0.053599711 | N84: 120.1717 | O84: 1145.002 | P84: =IF(OR(O84="",L84="",L84=0),"",O84/L84) -> 0.038724029 | Q84: 21192 | R84: =IF(OR(Q84="",Q72=""),"",Q84/Q72-1) -> 0.019728611 | S84: 7.154 | T84: 100.4309 | U84: =IF(OR(T84="",T72=""),"",T84/T72-1) -> -0.0040500083 | V84: 670668 | W84: =IF(OR(V84="",V72=""),"",V84/V72-1) -> 0.0045474153 | X84: 19909.6 | Y84: =IF(OR(X84="",X72=""),"",X84/X72-1) -> 0.055148657 | Z84: 17865.2 | AA84: =IF(OR(Z84="",Z72=""),"",Z84/Z72-1) -> 0.029783555 | AB84: 325.003 | AC84: =IF(OR(AB84="",AB72=""),"",AB84/AB72-1) -> 0.043070386 | AD84: 80.36 | AE84: 76.6832 | AF84: 2470 | AG84: =IF(OR(AF84="",AF72=""),"",AF84/AF72-1) -> 0.28712871 | AH84: 15 | AI84: 1.102
A85: 45536 | B85: 5621.26 | C85: =IF(OR(B85="",B73=""),"",B85/B73-1) -> 0.24480653 | D85: 3.72 | E85: 4.028 | F85: 5.13 | G85: =IF(OR(D85="",E85=""),"",D85-E85) -> -0.308 | H85: 315.301 | I85: =IF(OR(H85="",H73=""),"",H85/H73-1) -> 0.02440633 | J85: 4.1 | K85: 0.53 | L85: 29568.256 | M85: =IF(OR(L85="",L73=""),"",L85/L73-1) -> 0.053599711 | N85: 120.1717 | O85: 1145.002 | P85: =IF(OR(O85="",L85="",L85=0),"",O85/L85) -> 0.038724029 | Q85: 21275.6 | R85: =IF(OR(Q85="",Q73=""),"",Q85/Q73-1) -> 0.025152263 | S85: 7.1042 | T85: 99.8084 | U85: =IF(OR(T85="",T73=""),"",T85/T73-1) -> -0.012004423 | V85: 676005 | W85: =IF(OR(V85="",V73=""),"",V85/V73-1) -> 0.0073148998 | X85: 20066.9 | Y85: =IF(OR(X85="",X73=""),"",X85/X73-1) -> 0.057009365 | Z85: 17875.4 | AA85: =IF(OR(Z85="",Z73=""),"",Z85/Z73-1) -> 0.029125766 | AB85: 324.621 | AC85: =IF(OR(AB85="",AB73=""),"",AB85/AB73-1) -> 0.038986685 | AD85: 74.02 | AE85: 70.236 | AF85: 2571 | AG85: =IF(OR(AF85="",AF73=""),"",AF85/AF73-1) -> 0.34185804 | AH85: 16.73 | AI85: 1.1104
A86: 45566 | B86: 5792.32 | C86: =IF(OR(B86="",B74=""),"",B86/B74-1) -> 0.35670586 | D86: 4.1 | E86: 4.2 | F86: 4.83 | G86: =IF(OR(D86="",E86=""),"",D86-E86) -> -0.1 | H86: 315.664 | I86: =IF(OR(H86="",H74=""),"",H86/H74-1) -> 0.025979049 | J86: 4.1 | K86: 0.4 | L86: 29929.552 | M86: =IF(OR(L86="",L74=""),"",L86/L74-1) -> 0.051476611 | N86: 121.4363 | O86: 1166.444 | P86: =IF(OR(O86="",L86="",L86=0),"",O86/L86) -> 0.038972986 | Q86: 21336.6 | R86: =IF(OR(Q86="",Q74=""),"",Q86/Q74-1) -> 0.028894654 | S86: 7.0352 | T86: 99.4695 | U86: =IF(OR(T86="",T74=""),"",T86/T74-1) -> -0.0099473568 | V86: 681808 | W86: =IF(OR(V86="",V74=""),"",V86/V74-1) -> 0.020953408 | X86: 20146.1 | Y86: =IF(OR(X86="",X74=""),"",X86/X74-1) -> 0.056983211 | Z86: 17914.4 | AA86: =IF(OR(Z86="",Z74=""),"",Z86/Z74-1) -> 0.027443378 | AB86: 323.937 | AC86: =IF(OR(AB86="",AB74=""),"",AB86/AB74-1) -> 0.035630707 | AD86: 75.63 | AE86: 71.985 | AF86: 2690 | AG86: =IF(OR(AF86="",AF74=""),"",AF86/AF74-1) -> 0.4039666 | AH86: 23.16 | AI86: 1.0895
A87: 45597 | B87: 5929.92 | C87: =IF(OR(B87="",B75=""),"",B87/B75-1) -> 0.32956059 | D87: 4.36 | E87: 4.3332 | F87: 4.64 | G87: =IF(OR(D87="",E87=""),"",D87-E87) -> 0.0268 | H87: 315.493 | I87: =IF(OR(H87="",H75=""),"",H87/H75-1) -> 0.027493804 | J87: 4.2 | K87: 0.4 | L87: 29929.552 | M87: =IF(OR(L87="",L75=""),"",L87/L75-1) -> 0.051476611 | N87: 121.4363 | O87: 1166.444 | P87: =IF(OR(O87="",L87="",L87=0),"",O87/L87) -> 0.038972986 | Q87: 21454.7 | R87: =IF(OR(Q87="",Q75=""),"",Q87/Q75-1) -> 0.033976395 | S87: 6.9476 | T87: 99.2925 | U87: =IF(OR(T87="",T75=""),"",T87/T75-1) -> -0.015579409 | V87: 685709 | W87: =IF(OR(V87="",V75=""),"",V87/V75-1) -> 0.028945753 | X87: 20251.8 | Y87: =IF(OR(X87="",X75=""),"",X87/X75-1) -> 0.058292355 | Z87: 17955.4 | AA87: =IF(OR(Z87="",Z75=""),"",Z87/Z75-1) -> 0.024570894 | AB87: 323.654 | AC87: =IF(OR(AB87="",AB75=""),"",AB87/AB75-1) -> 0.037242856 | AD87: 74.35 | AE87: 69.95 | AF87: 2651 | AG87: =IF(OR(AF87="",AF75=""),"",AF87/AF75-1) -> 0.33618952 | AH87: 13.51 | AI87: 1.0621
A88: 45627 | B88: 6010.91 | C88: =IF(OR(B88="",B76=""),"",B88/B76-1) -> 0.28299805 | D88: 4.39 | E88: 4.2338 | F88: 4.48 | G88: =IF(OR(D88="",E88=""),"",D88-E88) -> 0.1562 | H88: 315.605 | I88: =IF(OR(H88="",H76=""),"",H88/H76-1) -> 0.028880572 | J88: 4.1 | K88: 0.4 | L88: 29929.552 | M88: =IF(OR(L88="",L76=""),"",L88/L76-1) -> 0.051476611 | N88: 121.4363 | O88: 1166.444 | P88: =IF(OR(O88="",L88="",L88=0),"",O88/L88) -> 0.038972986 | Q88: 21487.6 | R88: =IF(OR(Q88="",Q76=""),"",Q88/Q76-1) -> 0.034056949 | S88: 6.8922 | T88: 100.3273 | U88: =IF(OR(T88="",T76=""),"",T88/T76-1) -> -0.0027414662 | V88: 691794 | W88: =IF(OR(V88="",V76=""),"",V88/V76-1) -> 0.037229951 | X88: 20458.7 | Y88: =IF(OR(X88="",X76=""),"",X88/X76-1) -> 0.064836309 | Z88: 17963.9 | AA88: =IF(OR(Z88="",Z76=""),"",Z88/Z76-1) -> 0.021291232 | AB88: 323.275 | AC88: =IF(OR(AB88="",AB76=""),"",AB88/AB76-1) -> 0.039971047 | AD88: 73.86 | AE88: 70.1181 | AF88: 2648 | AG88: =IF(OR(AF88="",AF76=""),"",AF88/AF76-1) -> 0.30700888 | AH88: 17.35 | AI88: 1.0472 | AJ88: 4.25
A89: 45658 | B89: 5979.52 | C89: =IF(OR(B89="",B77=""),"",B89/B77-1) -> 0.24456914 | D89: 4.63 | E89: 4.1848 | F89: 4.33 | G89: =IF(OR(D89="",E89=""),"",D89-E89) -> 0.4452 | H89: 317.671 | I89: =IF(OR(H89="",H77=""),"",H89/H77-1) -> 0.030004831 | J89: 4 | K89: 0.37 | L89: 30171.979 | M89: =IF(OR(L89="",L77=""),"",L89/L77-1) -> 0.047885905 | N89: 120.5452 | O89: 1170.484 | P89: =IF(OR(O89="",L89="",L89=0),"",O89/L89) -> 0.038793743 | Q89: 21539.3 | R89: =IF(OR(Q89="",Q77=""),"",Q89/Q77-1) -> 0.033778887 | S89: 6.838 | T89: 100.0647 | U89: =IF(OR(T89="",T77=""),"",T89/T77-1) -> 0.0084900269 | V89: 687058 | W89: =IF(OR(V89="",V77=""),"",V89/V77-1) -> 0.04004832 | X89: 20400.4 | Y89: =IF(OR(X89="",X77=""),"",X89/X77-1) -> 0.060333895 | Z89: 17955.6 | AA89: =IF(OR(Z89="",Z77=""),"",Z89/Z77-1) -> 0.015611213 | AB89: 323.631 | AC89: =IF(OR(AB89="",AB77=""),"",AB89/AB77-1) -> 0.041575344 | AD89: 79.27 | AE89: 75.7425 | AF89: 2710 | AG89: =IF(OR(AF89="",AF77=""),"",AF89/AF77-1) -> 0.33235005 | AH89: 16.43 | AI89: 1.0356
A90: 45689 | B90: 6038.69 | C90: =IF(OR(B90="",B78=""),"",B90/B78-1) -> 0.20485598 | D90: 4.45 | E90: 4.1942 | F90: 4.33 | G90: =IF(OR(D90="",E90=""),"",D90-E90) -> 0.2558 | H90: 319.082 | I90: =IF(OR(H90="",H78=""),"",H90/H78-1) -> 0.02821549 | J90: 4.2 | K90: 0.3 | L90: 30171.979 | M90: =IF(OR(L90="",L78=""),"",L90/L78-1) -> 0.047885905 | N90: 120.5452 | O90: 1170.484 | P90: =IF(OR(O90="",L90="",L90=0),"",O90/L90) -> 0.038793743 | Q90: 21607.2 | R90: =IF(OR(Q90="",Q78=""),"",Q90/Q78-1) -> 0.032765024 | S90: 6.7932 | T90: 101.0993 | U90: =IF(OR(T90="",T78=""),"",T90/T78-1) -> 0.0081198584 | V90: 683772 | W90: =IF(OR(V90="",V78=""),"",V90/V78-1) -> 0.028814919 | X90: 20437.9 | Y90: =IF(OR(X90="",X78=""),"",X90/X78-1) -> 0.054941028 | Z90: 17957.4 | AA90: =IF(OR(Z90="",Z78=""),"",Z90/Z78-1) -> 0.0156326 | AB90: 325.097 | AC90: =IF(OR(AB90="",AB78=""),"",AB90/AB78-1) -> 0.039894442 | AD90: 75.44 | AE90: 71.5332 | AF90: 2895 | AG90: =IF(OR(AF90="",AF78=""),"",AF90/AF78-1) -> 0.43104301 | AH90: 19.63 | AI90: 1.0413
A91: 45717 | B91: 5683.98 | C91: =IF(OR(B91="",B79=""),"",B91/B79-1) -> 0.099294662 | D91: 4.28 | E91: 4.0638 | F91: 4.33 | G91: =IF(OR(D91="",E91=""),"",D91-E91) -> 0.2162 | H91: 319.799 | I91: =IF(OR(H91="",H79=""),"",H91/H79-1) -> 0.023907253 | J91: 4.2 | K91: 0.3 | L91: 30171.979 | M91: =IF(OR(L91="",L79=""),"",L91/L79-1) -> 0.047885905 | N91: 120.5452 | O91: 1170.484 | P91: =IF(OR(O91="",L91="",L91=0),"",O91/L91) -> 0.038793743 | Q91: 21684.1 | R91: =IF(OR(Q91="",Q79=""),"",Q91/Q79-1) -> 0.034255625 | S91: 6.7531 | T91: 101.0404 | U91: =IF(OR(T91="",T79=""),"",T91/T79-1) -> 0.0058024538 | V91: 694750 | W91: =IF(OR(V91="",V79=""),"",V91/V79-1) -> 0.045793644 | X91: 20594 | Y91: =IF(OR(X91="",X79=""),"",X91/X79-1) -> 0.055361105 | Z91: 18073 | AA91: =IF(OR(Z91="",Z79=""),"",Z91/Z79-1) -> 0.021119599 | AB91: 327.696 | AC91: =IF(OR(AB91="",AB79=""),"",AB91/AB79-1) -> 0.034367819 | AD91: 72.73 | AE91: 68.239 | AF91: 2983 | AG91: =IF(OR(AF91="",AF79=""),"",AF91/AF79-1) -> 0.38229842 | AH91: 22.28 | AI91: 1.0813
A92: 45748 | B92: 5369.5 | C92: =IF(OR(B92="",B80=""),"",B92/B80-1) -> 0.050271003 | D92: 4.28 | E92: 3.9529 | F92: 4.33 | G92: =IF(OR(D92="",E92=""),"",D92-E92) -> 0.3271 | H92: 320.795 | I92: =IF(OR(H92="",H80=""),"",H92/H80-1) -> 0.023112889 | J92: 4.2 | K92: 0.3 | L92: 30630.174 | M92: =IF(OR(L92="",L80=""),"",L92/L80-1) -> 0.047795701 | N92: 118.7817 | O92: 1197.132 | P92: =IF(OR(O92="",L92="",L92=0),"",O92/L92) -> 0.039083421 | Q92: 21770.8 | R92: =IF(OR(Q92="",Q80=""),"",Q92/Q80-1) -> 0.038911211 | S92: 6.7228 | T92: 101.1279 | U92: =IF(OR(T92="",T80=""),"",T92/T80-1) -> 0.0088235235 | V92: 695464 | W92: =IF(OR(V92="",V80=""),"",V92/V80-1) -> 0.04603389 | X92: 20654.2 | Y92: =IF(OR(X92="",X80=""),"",X92/X80-1) -> 0.054743594 | Z92: 18190.1 | AA92: =IF(OR(Z92="",Z80=""),"",Z92/Z80-1) -> 0.024956049 | AB92: 329.848 | AC92: =IF(OR(AB92="",AB80=""),"",AB92/AB80-1) -> 0.028371182 | AD92: 68.13 | AE92: 63.5367 | AF92: 3218 | AG92: =IF(OR(AF92="",AF80=""),"",AF92/AF80-1) -> 0.38052338 | AH92: 24.7 | AI92: 1.1232
A93: 45778 | B93: 5810.92 | C93: =IF(OR(B93="",B81=""),"",B93/B81-1) -> 0.10996461 | D93: 4.42 | E93: 4.0857 | F93: 4.33 | G93: =IF(OR(D93="",E93=""),"",D93-E93) -> 0.3343 | H93: 321.465 | I93: =IF(OR(H93="",H81=""),"",H93/H81-1) -> 0.023548965 | J93: 4.3 | K93: 0.33 | L93: 30630.174 | M93: =IF(OR(L93="",L81=""),"",L93/L81-1) -> 0.047795701 | N93: 118.7817 | O93: 1197.132 | P93: =IF(OR(O93="",L93="",L93=0),"",O93/L93) -> 0.039083421 | Q93: 21836.1 | R93: =IF(OR(Q93="",Q81=""),"",Q93/Q81-1) -> 0.038745861 | S93: 6.6965 | T93: 100.9655 | U93: =IF(OR(T93="",T81=""),"",T93/T81-1) -> 0.0010162299 | V93: 685488 | W93: =IF(OR(V93="",V81=""),"",V93/V81-1) -> 0.026703751 | X93: 20666.1 | Y93: =IF(OR(X93="",X81=""),"",X93/X81-1) -> 0.049626695 | Z93: 18072 | AA93: =IF(OR(Z93="",Z81=""),"",Z93/Z81-1) -> 0.01411296 | AB93: 331.367 | AC93: =IF(OR(AB93="",AB81=""),"",AB93/AB81-1) -> 0.023698161 | AD93: 64.45 | AE93: 62.1676 | AF93: 3309 | AG93: =IF(OR(AF93="",AF81=""),"",AF93/AF81-1) -> 0.40748618 | AH93: 18.57 | AI93: 1.1274
A94: 45809 | B94: 6029.95 | C94: =IF(OR(B94="",B82=""),"",B94/B82-1) -> 0.11353538 | D94: 4.38 | E94: 4.062 | F94: 4.33 | G94: =IF(OR(D94="",E94=""),"",D94-E94) -> 0.318 | H94: 322.561 | I94: =IF(OR(H94="",H82=""),"",H94/H82-1) -> 0.02669213 | J94: 4.1 | K94: 0.23 | L94: 30630.174 | M94: =IF(OR(L94="",L82=""),"",L94/L82-1) -> 0.047795701 | N94: 118.7817 | O94: 1197.132 | P94: =IF(OR(O94="",L94="",L94=0),"",O94/L94) -> 0.039083421 | Q94: 21942.6 | R94: =IF(OR(Q94="",Q82=""),"",Q94/Q82-1) -> 0.041379736 | S94: 6.6733 | T94: 101.4785 | U94: =IF(OR(T94="",T82=""),"",T94/T82-1) -> 0.0057932087 | V94: 691883 | W94: =IF(OR(V94="",V82=""),"",V94/V82-1) -> 0.038800973 | X94: 20799.4 | Y94: =IF(OR(X94="",X82=""),"",X94/X82-1) -> 0.051786825 | Z94: 18088.6 | AA94: =IF(OR(Z94="",Z82=""),"",Z94/Z82-1) -> 0.012244121 | AB94: 331.564 | AC94: =IF(OR(AB94="",AB82=""),"",AB94/AB82-1) -> 0.019393954 | AD94: 71.44 | AE94: 68.169 | AF94: 3353 | AG94: =IF(OR(AF94="",AF82=""),"",AF94/AF82-1) -> 0.44153052 | AH94: 16.73 | AI94: 1.1534 | AJ94: 3.72
A95: 45839 | B95: 6296.5 | C95: =IF(OR(B95="",B83=""),"",B95/B83-1) -> 0.1369628 | D95: 4.39 | E95: 4.0764 | F95: 4.33 | G95: =IF(OR(D95="",E95=""),"",D95-E95) -> 0.3136 | H95: 323.048 | I95: =IF(OR(H95="",H83=""),"",H95/H83-1) -> 0.027049024 | J95: 4.3 | K95: 0.17 | L95: 31180.493 | M95: =IF(OR(L95="",L83=""),"",L95/L83-1) -> 0.054525942 | N95: 121.0288 | O95: 1238.252 | P95: =IF(OR(O95="",L95="",L95=0),"",O95/L95) -> 0.039712393 | Q95: 22025.6 | R95: =IF(OR(Q95="",Q83=""),"",Q95/Q83-1) -> 0.043921721 | S95: 6.6562 | T95: 101.894 | U95: =IF(OR(T95="",T83=""),"",T95/T83-1) -> 0.019187663 | V95: 698280 | W95: =IF(OR(V95="",V83=""),"",V95/V83-1) -> 0.036543549 | X95: 20927.2 | Y95: =IF(OR(X95="",X83=""),"",X95/X83-1) -> 0.053545178 | Z95: 18144.4 | AA95: =IF(OR(Z95="",Z83=""),"",Z95/Z83-1) -> 0.015764606 | AB95: 330.923 | AC95: =IF(OR(AB95="",AB83=""),"",AB95/AB83-1) -> 0.016454421 | AD95: 71.04 | AE95: 68.3909 | AF95: 3340 | AG95: =IF(OR(AF95="",AF83=""),"",AF95/AF83-1) -> 0.39282736 | AH95: 16.72 | AI95: 1.1671
A96: 45870 | B96: 6408.95 | C96: =IF(OR(B96="",B84=""),"",B96/B84-1) -> 0.16989856 | D96: 4.26 | E96: 3.89 | F96: 4.33 | G96: =IF(OR(D96="",E96=""),"",D96-E96) -> 0.37 | H96: 323.976 | I96: =IF(OR(H96="",H84=""),"",H96/H84-1) -> 0.029161743 | J96: 4.3 | K96: 0.13 | L96: 31180.493 | M96: =IF(OR(L96="",L84=""),"",L96/L84-1) -> 0.054525942 | N96: 121.0288 | O96: 1238.252 | P96: =IF(OR(O96="",L96="",L96=0),"",O96/L96) -> 0.039712393 | Q96: 22092.6 | R96: =IF(OR(Q96="",Q84=""),"",Q96/Q84-1) -> 0.042497169 | S96: 6.6266 | T96: 101.6247 | U96: =IF(OR(T96="",T84=""),"",T96/T84-1) -> 0.01188678 | V96: 700218 | W96: =IF(OR(V96="",V84=""),"",V96/V84-1) -> 0.044060549 | X96: 21029.5 | Y96: =IF(OR(X96="",X84=""),"",X96/X84-1) -> 0.056249247 | Z96: 18174 | AA96: =IF(OR(Z96="",Z84=""),"",Z96/Z84-1) -> 0.017285001 | AB96: 329.845 | AC96: =IF(OR(AB96="",AB84=""),"",AB96/AB84-1) -> 0.014898324 | AD96: 67.87 | AE96: 64.8643 | AF96: 3368 | AG96: =IF(OR(AF96="",AF84=""),"",AF96/AF84-1) -> 0.36356275 | AH96: 15.36 | AI96: 1.1647
A97: 45901 | B97: 6584.02 | C97: =IF(OR(B97="",B85=""),"",B97/B85-1) -> 0.17127121 | D97: 4.12 | E97: 3.6605 | F97: 4.22 | G97: =IF(OR(D97="",E97=""),"",D97-E97) -> 0.4595 | H97: 324.8 | I97: =IF(OR(H97="",H85=""),"",H97/H85-1) -> 0.030126768 | J97: 4.4 | K97: 0.23 | L97: 31180.493 | M97: =IF(OR(L97="",L85=""),"",L97/L85-1) -> 0.054525942 | N97: 121.0288 | O97: 1238.252 | P97: =IF(OR(O97="",L97="",L97=0),"",O97/L97) -> 0.039712393 | Q97: 22176.1 | R97: =IF(OR(Q97="",Q85=""),"",Q97/Q85-1) -> 0.042325481 | S97: 6.6063 | T97: 101.668 | U97: =IF(OR(T97="",T85=""),"",T97/T85-1) -> 0.018631698 | V97: 701453 | W97: =IF(OR(V97="",V85=""),"",V97/V85-1) -> 0.037644692 | X97: 21126.5 | Y97: =IF(OR(X97="",X85=""),"",X97/X85-1) -> 0.052803373 | Z97: 18192.7 | AA97: =IF(OR(Z97="",Z85=""),"",Z97/Z85-1) -> 0.017750652 | AB97: 328.874 | AC97: =IF(OR(AB97="",AB85=""),"",AB97/AB85-1) -> 0.013101432 | AD97: 67.99 | AE97: 63.959 | AF97: 3668 | AG97: =IF(OR(AF97="",AF85=""),"",AF97/AF85-1) -> 0.42668222 | AH97: 16.28 | AI97: 1.1739
A98: 45931 | B98: 6735.69 | C98: =IF(OR(B98="",B86=""),"",B98/B86-1) -> 0.16286566 | D98: 4.06 | E98: 3.6141 | F98: 4.09 | G98: =IF(OR(D98="",E98=""),"",D98-E98) -> 0.4459 | I98: =IF(OR(H98="",H86=""),"",H98/H86-1) | K98: 0.25 | L98: 31462.523 | M98: =IF(OR(L98="",L86=""),"",L98/L86-1) -> 0.05121931 | N98: 122.5682 | O98: 1265.05 | P98: =IF(OR(O98="",L98="",L98=0),"",O98/L98) -> 0.040208155 | Q98: 22249.8 | R98: =IF(OR(Q98="",Q86=""),"",Q98/Q86-1) -> 0.042799696 | S98: 6.5902 | T98: 101.2195 | U98: =IF(OR(T98="",T86=""),"",T98/T86-1) -> 0.017593333 | V98: 700790 | W98: =IF(OR(V98="",V86=""),"",V98/V86-1) -> 0.027840682 | X98: 21196.4 | Y98: =IF(OR(X98="",X86=""),"",X98/X86-1) -> 0.05213416 | Z98: 18168.4 | AA98: =IF(OR(Z98="",Z86=""),"",Z98/Z86-1) -> 0.014178538 | AB98: 328.233 | AC98: =IF(OR(AB98="",AB86=""),"",AB98/AB86-1) -> 0.013261838 | AD98: 64.54 | AE98: 60.8945 | AF98: 4058 | AG98: =IF(OR(AF98="",AF86=""),"",AF98/AF86-1) -> 0.50855019 | AH98: 17.44 | AI98: 1.1641
A99: 45962 | B99: 6740.89 | C99: =IF(OR(B99="",B87=""),"",B99/B87-1) -> 0.13675901 | D99: 4.09 | E99: 3.655 | F99: 3.88 | G99: =IF(OR(D99="",E99=""),"",D99-E99) -> 0.435 | H99: 324.122 | I99: =IF(OR(H99="",H87=""),"",H99/H87-1) -> 0.027350845 | J99: 4.5 | K99: 0.35 | L99: 31462.523 | M99: =IF(OR(L99="",L87=""),"",L99/L87-1) -> 0.05121931 | N99: 122.5682 | O99: 1265.05 | P99: =IF(OR(O99="",L99="",L99=0),"",O99/L99) -> 0.040208155 | Q99: 22279.8 | R99: =IF(OR(Q99="",Q87=""),"",Q99/Q87-1) -> 0.038457774 | S99: 6.5652 | T99: 101.0344 | U99: =IF(OR(T99="",T87=""),"",T99/T87-1) -> 0.017543118 | V99: 705453 | W99: =IF(OR(V99="",V87=""),"",V99/V87-1) -> 0.028793555 | X99: 21274.2 | Y99: =IF(OR(X99="",X87=""),"",X99/X87-1) -> 0.050484401 | Z99: 18201.5 | AA99: =IF(OR(Z99="",Z87=""),"",Z99/Z87-1) -> 0.013706183 | AB99: 327.853 | AC99: =IF(OR(AB99="",AB87=""),"",AB99/AB87-1) -> 0.012973731 | AD99: 63.8 | AE99: 60.0622 | AF99: 4087 | AG99: =IF(OR(AF99="",AF87=""),"",AF99/AF87-1) -> 0.54168238 | AH99: 16.35 | AI99: 1.1558
A100: 45992 | B100: 6853.03 | C100: =IF(OR(B100="",B88=""),"",B100/B88-1) -> 0.14009859 | D100: 4.14 | E100: 3.5418 | F100: 3.72 | G100: =IF(OR(D100="",E100=""),"",D100-E100) -> 0.5982 | H100: 324.054 | I100: =IF(OR(H100="",H88=""),"",H100/H88-1) -> 0.026770805 | J100: 4.4 | K100: 0.35 | L100: 31462.523 | M100: =IF(OR(L100="",L88=""),"",L100/L88-1) -> 0.05121931 | N100: 122.5682 | O100: 1265.05 | P100: =IF(OR(O100="",L100="",L100=0),"",O100/L100) -> 0.040208155 | Q100: 22355.3 | R100: =IF(OR(Q100="",Q88=""),"",Q100/Q88-1) -> 0.040381429 | S100: 6.5708 | T100: 101.4941 | U100: =IF(OR(T100="",T88=""),"",T100/T88-1) -> 0.011629935 | V100: 706264 | W100: =IF(OR(V100="",V88=""),"",V100/V88-1) -> 0.020916631 | X100: 21336 | Y100: =IF(OR(X100="",X88=""),"",X100/X88-1) -> 0.042881513 | Z100: 18208.6 | AA100: =IF(OR(Z100="",Z88=""),"",Z100/Z88-1) -> 0.013621764 | AB100: 327.028 | AC100: =IF(OR(AB100="",AB88=""),"",AB100/AB88-1) -> 0.011609311 | AD100: 62.54 | AE100: 57.9723 | AF100: 4309 | AG100: =IF(OR(AF100="",AF88=""),"",AF100/AF88-1) -> 0.62726586 | AH100: 14.95 | AI100: 1.171 | AJ100: 3.5
A101: 46023 | B101: 6929.12 | C101: =IF(OR(B101="",B89=""),"",B101/B89-1) -> 0.15880873 | D101: 4.21 | E101: 3.5085 | F101: 3.64 | G101: =IF(OR(D101="",E101=""),"",D101-E101) -> 0.7015 | H101: 325.252 | I101: =IF(OR(H101="",H89=""),"",H101/H89-1) -> 0.023864312 | J101: 4.3 | K101: 0.3 | L101: 31906.274 | M101: =IF(OR(L101="",L89=""),"",L101/L89-1) -> 0.05748032 | N101: 122.5939 | O101: 1252.858 | P101: =IF(OR(O101="",L101="",L101=0),"",O101/L101) -> 0.039266823 | Q101: 22413.4 | R101: =IF(OR(Q101="",Q89=""),"",Q101/Q89-1) -> 0.040581635 | S101: 6.5819 | T101: 101.0388 | U101: =IF(OR(T101="",T89=""),"",T101/T89-1) -> 0.0097347016 | V101: 701860 | W101: =IF(OR(V101="",V89=""),"",V101/V89-1) -> 0.021544033 | X101: 21383.1 | Y101: =IF(OR(X101="",X89=""),"",X101/X89-1) -> 0.048170624 | Z101: 18322.5 | AA101: =IF(OR(Z101="",Z89=""),"",Z101/Z89-1) -> 0.020433737 | AB101: 326.764 | AC101: =IF(OR(AB101="",AB89=""),"",AB101/AB89-1) -> 0.0096807784 | AD101: 66.6 | AE101: 60.037 | AF101: 4753 | AG101: =IF(OR(AF101="",AF89=""),"",AF101/AF89-1) -> 0.75387454 | AH101: 17.44 | AI101: 1.1744
A102: 46054 | B102: 6893.81 | C102: =IF(OR(B102="",B90=""),"",B102/B90-1) -> 0.14160687 | D102: 4.13 | E102: 3.4768 | F102: 3.64 | G102: =IF(OR(D102="",E102=""),"",D102-E102) -> 0.6532 | H102: 326.785 | I102: =IF(OR(H102="",H90=""),"",H102/H90-1) -> 0.02414113 | J102: 4.4 | K102: 0.27 | L102: 31906.274 | M102: =IF(OR(L102="",L90=""),"",L102/L90-1) -> 0.05748032 | N102: 122.5939 | O102: 1252.858 | P102: =IF(OR(O102="",L102="",L102=0),"",O102/L102) -> 0.039266823 | Q102: 22598.7 | R102: =IF(OR(Q102="",Q90=""),"",Q102/Q90-1) -> 0.045887482 | S102: 6.6139 | T102: 101.9053 | U102: =IF(OR(T102="",T90=""),"",T102/T90-1) -> 0.0079723598 | V102: 707959 | W102: =IF(OR(V102="",V90=""),"",V102/V90-1) -> 0.035372902 | X102: 21502 | Y102: =IF(OR(X102="",X90=""),"",X102/X90-1) -> 0.052065036 | Z102: 18284.8 | AA102: =IF(OR(Z102="",Z90=""),"",Z102/Z90-1) -> 0.018232038 | AB102: 327.824 | AC102: =IF(OR(AB102="",AB90=""),"",AB102/AB90-1) -> 0.0083882657 | AD102: 70.89 | AE102: 64.5084 | AF102: 5020 | AG102: =IF(OR(AF102="",AF90=""),"",AF102/AF90-1) -> 0.73402418 | AH102: 19.86 | AI102: 1.1824
A103: 46082 | B103: 6654.42 | C103: =IF(OR(B103="",B91=""),"",B103/B91-1) -> 0.17073248 | D103: 4.25 | E103: 3.6664 | F103: 3.64 | G103: =IF(OR(D103="",E103=""),"",D103-E103) -> 0.5836 | H103: 330.213 | I103: =IF(OR(H103="",H91=""),"",H103/H91-1) -> 0.032564204 | J103: 4.3 | K103: 0.2 | L103: 31906.274 | M103: =IF(OR(L103="",L91=""),"",L103/L91-1) -> 0.05748032 | N103: 122.5939 | O103: 1252.858 | P103: =IF(OR(O103="",L103="",L103=0),"",O103/L103) -> 0.039266823 | Q103: 22640.3 | R103: =IF(OR(Q103="",Q91=""),"",Q103/Q91-1) -> 0.044096827 | S103: 6.6471 | T103: 101.7336 | U103: =IF(OR(T103="",T91=""),"",T103/T91-1) -> 0.0068606221 | V103: 719700 | W103: =IF(OR(V103="",V91=""),"",V103/V91-1) -> 0.035912199 | X103: 21692.9 | Y103: =IF(OR(X103="",X91=""),"",X103/X91-1) -> 0.053360202 | Z103: 18301.6 | AA103: =IF(OR(Z103="",Z91=""),"",Z103/Z91-1) -> 0.012648702 | AB103: 330.408 | AC103: =IF(OR(AB103="",AB91=""),"",AB103/AB91-1) -> 0.0082759631 | AD103: 103.13 | AE103: 91.3836 | AF103: 4856 | AG103: =IF(OR(AF103="",AF91=""),"",AF103/AF91-1) -> 0.62789138 | AH103: 25.25 | AI103: 1.1557
A104: 46113 | B104: 6957.01 | C104: =IF(OR(B104="",B92=""),"",B104/B92-1) -> 0.29565323 | D104: 4.32 | E104: 3.6936 | F104: 3.64 | G104: =IF(OR(D104="",E104=""),"",D104-E104) -> 0.6264 | H104: 333.02 | I104: =IF(OR(H104="",H92=""),"",H104/H92-1) -> 0.038108449 | J104: 4.3 | K104: 0.13 | L104: 32563.03 | M104: =IF(OR(L104="",L92=""),"",L104/L92-1) -> 0.063103004 | O104: 1279.734 | P104: =IF(OR(O104="",L104="",L104=0),"",O104/L104) -> 0.039300213 | Q104: 22756.6 | R104: =IF(OR(Q104="",Q92=""),"",Q104/Q92-1) -> 0.045280835 | S104: 6.6965 | T104: 102.5783 | U104: =IF(OR(T104="",T92=""),"",T104/T92-1) -> 0.014342234 | V104: 723921 | W104: =IF(OR(V104="",V92=""),"",V104/V92-1) -> 0.040918006 | X104: 21856.9 | Y104: =IF(OR(X104="",X92=""),"",X104/X92-1) -> 0.058230287 | Z104: 18231.9 | AA104: =IF(OR(Z104="",Z92=""),"",Z104/Z92-1) -> 0.0022979533 | AB104: 333.15 | AC104: =IF(OR(AB104="",AB92=""),"",AB104/AB92-1) -> 0.010010672 | AD104: 117.29 | AE104: 100.3167 | AF104: 4721 | AG104: =IF(OR(AF104="",AF92=""),"",AF104/AF92-1) -> 0.46706029 | AH104: 16.89 | AI104: 1.1697
A105: 46143 | B105: 7412.55 | C105: =IF(OR(B105="",B93=""),"",B105/B93-1) -> 0.27562417 | D105: 4.48 | E105: 3.792 | F105: 3.63 | G105: =IF(OR(D105="",E105=""),"",D105-E105) -> 0.688 | H105: 335.123 | I105: =IF(OR(H105="",H93=""),"",H105/H93-1) -> 0.04248674 | J105: 4.3 | K105: 0.1 | L105: 32563.03 | M105: =IF(OR(L105="",L93=""),"",L105/L93-1) -> 0.063103004 | O105: 1279.734 | P105: =IF(OR(O105="",L105="",L105=0),"",O105/L105) -> 0.039300213 | Q105: 23013.7 | R105: =IF(OR(Q105="",Q93=""),"",Q105/Q93-1) -> 0.053929044 | S105: 6.714 | T105: 102.6396 | U105: =IF(OR(T105="",T93=""),"",T105/T93-1) -> 0.016580911 | V105: 731415 | W105: =IF(OR(V105="",V93=""),"",V105/V93-1) -> 0.066998985 | X105: 22027.2 | Y105: =IF(OR(X105="",X93=""),"",X105/X93-1) -> 0.065861483 | Z105: 18292.8 | AA105: =IF(OR(Z105="",Z93=""),"",Z105/Z93-1) -> 0.012217795 | AB105: 335.584 | AC105: =IF(OR(AB105="",AB93=""),"",AB105/AB93-1) -> 0.012726071 | AD105: 107.14 | AE105: 102.134 | AF105: 4587 | AG105: =IF(OR(AF105="",AF93=""),"",AF105/AF93-1) -> 0.3862194 | AH105: 15.32 | AI105: 1.1681
A106: 46174 | B106: 7450.03 | C106: =IF(OR(B106="",B94=""),"",B106/B94-1) -> 0.23550444 | D106: 4.47 | E106: 3.9095 | F106: 3.63 | G106: =IF(OR(D106="",E106=""),"",D106-E106) -> 0.5605 | H106: 333.952 | I106: =IF(OR(H106="",H94=""),"",H106/H94-1) -> 0.035314251 | J106: 4.2 | K106: 0.07 | L106: 32563.03 | M106: =IF(OR(L106="",L94=""),"",L106/L94-1) -> 0.063103004 | O106: 1279.734 | P106: =IF(OR(O106="",L106="",L106=0),"",O106/L106) -> 0.039300213 | Q106: 23114.9 | R106: =IF(OR(Q106="",Q94=""),"",Q106/Q94-1) -> 0.053425756 | S106: 6.7272 | T106: 102.842 | U106: =IF(OR(T106="",T94=""),"",T106/T94-1) -> 0.013436344 | V106: 732898 | W106: =IF(OR(V106="",V94=""),"",V106/V94-1) -> 0.059280254 | X106: 22095.5 | Y106: =IF(OR(X106="",X94=""),"",X106/X94-1) -> 0.062314298 | Z106: 18358.4 | AA106: =IF(OR(Z106="",Z94=""),"",Z106/Z94-1) -> 0.014915472 | AB106: 336.908 | AC106: =IF(OR(AB106="",AB94=""),"",AB106/AB94-1) -> 0.016117552 | AD106: 85.4 | AE106: 84.8071 | AF106: 4228 | AG106: =IF(OR(AF106="",AF94=""),"",AF106/AF94-1) -> 0.26096033 | AH106: 16.45 | AI106: 1.1516
A107: 46204 | B107: 7481.34 | C107: =IF(OR(B107="",B95=""),"",B107/B95-1) -> 0.18817438 | D107: 4.6 | E107: 4.0509 | F107: 3.63 | G107: =IF(OR(D107="",E107=""),"",D107-E107) -> 0.5491 | H107: 333.918 | I107: =IF(OR(H107="",H95=""),"",H107/H95-1) -> 0.03364825 | J107: 4.1 | K107: -0.03 | M107: =IF(OR(L107="",L95=""),"",L107/L95-1) | P107: =IF(OR(O107="",L107="",L107=0),"",O107/L107) | Q107: 23217.9 | R107: =IF(OR(Q107="",Q95=""),"",Q107/Q95-1) -> 0.054132464 | S107: 6.7378 | T107: 103.0454 | U107: =IF(OR(T107="",T95=""),"",T107/T95-1) -> 0.011299978 | V107: 729538 | W107: =IF(OR(V107="",V95=""),"",V107/V95-1) -> 0.044764278 | X107: 22117.7 | Y107: =IF(OR(X107="",X95=""),"",X107/X95-1) -> 0.056887687 | Z107: 18415.4 | AA107: =IF(OR(Z107="",Z95=""),"",Z107/Z95-1) -> 0.014935738 | AB107: 337.306 | AC107: =IF(OR(AB107="",AB95=""),"",AB107/AB95-1) -> 0.019288475 | AD107: 83.76 | AE107: 80.4564 | AF107: 4073 | AG107: =IF(OR(AF107="",AF95=""),"",AF107/AF95-1) -> 0.21946108 | AH107: 15.99 | AI107: 1.1423
A108: 46235 | B108: 7711.32 | C108: =IF(OR(B108="",B96=""),"",B108/B96-1) -> 0.20321113 | D108: 4.68 | E108: 4.0314 | F108: 3.63 | G108: =IF(OR(D108="",E108=""),"",D108-E108) -> 0.6486 | H108: 334.98 | I108: =IF(OR(H108="",H96=""),"",H108/H96-1) -> 0.033965479 | J108: 4.1 | K108: -0.07 | M108: =IF(OR(L108="",L96=""),"",L108/L96-1) | P108: =IF(OR(O108="",L108="",L108=0),"",O108/L108) | Q108: 23342.8 | R108: =IF(OR(Q108="",Q96=""),"",Q108/Q96-1) -> 0.056589084 | S108: 6.7463 | T108: 103.0682 | U108: =IF(OR(T108="",T96=""),"",T108/T96-1) -> 0.014204224 | V108: 737763 | W108: =IF(OR(V108="",V96=""),"",V108/V96-1) -> 0.053619016 | X108: 22308.5 | Y108: =IF(OR(X108="",X96=""),"",X108/X96-1) -> 0.060819325 | Z108: 18410.5 | AA108: =IF(OR(Z108="",Z96=""),"",Z108/Z96-1) -> 0.013013096 | AC108: =IF(OR(AB108="",AB96=""),"",AB108/AB96-1) | AD108: 91.08 | AE108: 83.8976 | AF108: 4411 | AG108: =IF(OR(AF108="",AF96=""),"",AF108/AF96-1) -> 0.30967933 | AH108: 14.92 | AI108: 1.1594
A109: 46266 | B109: 7669.41 | C109: =IF(OR(B109="",B97=""),"",B109/B97-1) -> 0.16485217 | E109: 4.3652 | F109: 3.75 | G109: =IF(OR(D109="",E109=""),"",D109-E109) | I109: =IF(OR(H109="",H97=""),"",H109/H97-1) | J109: 4.2 | K109: 0 | M109: =IF(OR(L109="",L97=""),"",L109/L97-1) | P109: =IF(OR(O109="",L109="",L109=0),"",O109/L109) | R109: =IF(OR(Q109="",Q97=""),"",Q109/Q97-1) | S109: 6.743 | U109: =IF(OR(T109="",T97=""),"",T109/T97-1) | W109: =IF(OR(V109="",V97=""),"",V109/V97-1) | Y109: =IF(OR(X109="",X97=""),"",X109/X97-1) | AA109: =IF(OR(Z109="",Z97=""),"",Z109/Z97-1) | AC109: =IF(OR(AB109="",AB97=""),"",AB109/AB97-1) | AD109: 114.16 | AE109: 97.3081 | AF109: 4319 | AG109: =IF(OR(AF109="",AF97=""),"",AF109/AF97-1) -> 0.17748092 | AH109: 14.21 | AI109: 1.1505 | AJ109: 4.75

Sheet Anchors
A1: Sparse anchor values for series not available from a reachable data feed
A2: These are point values only. Cells marked "memory" are approximate recollections of the published series and must be verified on FRED, BEA, CBO or FactSet before any decision rests on them. Cells marked "brief" come from the 4 Oct 2026 research briefs (web-sourced, unaudited).
A4: Series | B4: Month | C4: Value | D4: Source / note
A5: Core PCE inflation y/y (%) | B5: 43435 | C5: 2 | D5: Approximate value from analyst memory of the published series; verify on FRED/FactSet before relying on it
A6: Core PCE inflation y/y (%) | B6: 43800 | C6: 1.6 | D6: Approximate value from analyst memory of the published series; verify on FRED/FactSet before relying on it
A7: Core PCE inflation y/y (%) | B7: 44166 | C7: 1.5 | D7: Approximate value from analyst memory of the published series; verify on FRED/FactSet before relying on it
A8: Core PCE inflation y/y (%) | B8: 44348 | C8: 3.6 | D8: Approximate value from analyst memory of the published series; verify on FRED/FactSet before relying on it
A9: Core PCE inflation y/y (%) | B9: 44531 | C9: 4.9 | D9: Approximate value from analyst memory of the published series; verify on FRED/FactSet before relying on it
A10: Core PCE inflation y/y (%) | B10: 44593 | C10: 5.4 | D10: Approximate value from analyst memory of the published series; verify on FRED/FactSet before relying on it
A11: Core PCE inflation y/y (%) | B11: 44713 | C11: 4.9 | D11: Approximate value from analyst memory of the published series; verify on FRED/FactSet before relying on it
A12: Core PCE inflation y/y (%) | B12: 44896 | C12: 4.6 | D12: Approximate value from analyst memory of the published series; verify on FRED/FactSet before relying on it
A13: Core PCE inflation y/y (%) | B13: 45078 | C13: 4.1 | D13: Approximate value from analyst memory of the published series; verify on FRED/FactSet before relying on it
A14: Core PCE inflation y/y (%) | B14: 45261 | C14: 2.9 | D14: Approximate value from analyst memory of the published series; verify on FRED/FactSet before relying on it
A15: Core PCE inflation y/y (%) | B15: 45444 | C15: 2.6 | D15: Approximate value from analyst memory of the published series; verify on FRED/FactSet before relying on it
A16: Core PCE inflation y/y (%) | B16: 45627 | C16: 2.8 | D16: Approximate value from analyst memory of the published series; verify on FRED/FactSet before relying on it
... A100: Fed funds target range, upper (%) | B100: 46266 | C100: 4 | D100: Research brief, 4 Oct 2026 (council-reports/research-*.md), web-sourced, unaudited (hike 16 Sep 2026)

Sheet Snapshot
A1: Snapshot at selected months (all cells are INDEX/MATCH formulas into the Monthly sheet)
A3: Metric | B3: 43800 | C3: 43983 | D3: 44531 | E3: 44713 | F3: 44896 | G3: 45261 | H3: 45627 | I3: 45809 | J3: 45992 | K3: 46082 | L3: 46174 | M3: 46266
A4: S&P 500 (monthly avg) | B4: =IFERROR(INDEX(Monthly!$B$5:$B$109,MATCH(B$3,Monthly!$A$5:$A$109,0)),"") -> 3176.7495 | C4: =IFERROR(INDEX(Monthly!$B$5:$B$109,MATCH(C$3,Monthly!$A$5:$A$109,0)),"") -> 3104.6609 | D4: =IFERROR(INDEX(Monthly!$B$5:$B$109,MATCH(D$3,Monthly!$A$5:$A$109,0)),"") -> 4674.7727 | E4: =IFERROR(INDEX(Monthly!$B$5:$B$109,MATCH(E$3,Monthly!$A$5:$A$109,0)),"") -> 3898.9467 | F4: =IFERROR(INDEX(Monthly!$B$5:$B$109,MATCH(F$3,Monthly!$A$5:$A$109,0)),"") -> 3912.381 | G4: =IFERROR(INDEX(Monthly!$B$5:$B$109,MATCH(G$3,Monthly!$A$5:$A$109,0)),"") -> 4685.05 | H4: =IFERROR(INDEX(Monthly!$B$5:$B$109,MATCH(H$3,Monthly!$A$5:$A$109,0)),"") -> 6010.91 | I4: =IFERROR(INDEX(Monthly!$B$5:$B$109,MATCH(I$3,Monthly!$A$5:$A$109,0)),"") -> 6029.95 | ... M4: =IFERROR(INDEX(Monthly!$B$5:$B$109,MATCH(M$3,Monthly!$A$5:$A$109,0)),"") -> 7669.41
A5: S&P 500 y/y | B5: =IFERROR(INDEX(Monthly!$C$5:$C$109,MATCH(B$3,Monthly!$A$5:$A$109,0)),"") -> 0.23738446 | C5: =IFERROR(INDEX(Monthly!$C$5:$C$109,MATCH(C$3,Monthly!$A$5:$A$109,0)),"") -> 0.074213939 | D5: =IFERROR(INDEX(Monthly!$C$5:$C$109,MATCH(D$3,Monthly!$A$5:$A$109,0)),"") -> 0.26505562 | E5: =IFERROR(INDEX(Monthly!$C$5:$C$109,MATCH(E$3,Monthly!$A$5:$A$109,0)),"") -> -0.080109388 | F5: =IFERROR(INDEX(Monthly!$C$5:$C$109,MATCH(F$3,Monthly!$A$5:$A$109,0)),"") -> -0.16308637 | G5: =IFERROR(INDEX(Monthly!$C$5:$C$109,MATCH(G$3,Monthly!$A$5:$A$109,0)),"") -> 0.19749329 | H5: =IFERROR(INDEX(Monthly!$C$5:$C$109,MATCH(H$3,Monthly!$A$5:$A$109,0)),"") -> 0.28299805 | I5: =IFERROR(INDEX(Monthly!$C$5:$C$109,MATCH(I$3,Monthly!$A$5:$A$109,0)),"") -> 0.11353538 | ... M5: =IFERROR(INDEX(Monthly!$C$5:$C$109,MATCH(M$3,Monthly!$A$5:$A$109,0)),"") -> 0.16485217
A6: 10y Treasury yield (%) | B6: =IFERROR(INDEX(Monthly!$D$5:$D$109,MATCH(B$3,Monthly!$A$5:$A$109,0)),"") -> 1.86 | C6: =IFERROR(INDEX(Monthly!$D$5:$D$109,MATCH(C$3,Monthly!$A$5:$A$109,0)),"") -> 0.73 | D6: =IFERROR(INDEX(Monthly!$D$5:$D$109,MATCH(D$3,Monthly!$A$5:$A$109,0)),"") -> 1.47 | E6: =IFERROR(INDEX(Monthly!$D$5:$D$109,MATCH(E$3,Monthly!$A$5:$A$109,0)),"") -> 3.14 | F6: =IFERROR(INDEX(Monthly!$D$5:$D$109,MATCH(F$3,Monthly!$A$5:$A$109,0)),"") -> 3.62 | G6: =IFERROR(INDEX(Monthly!$D$5:$D$109,MATCH(G$3,Monthly!$A$5:$A$109,0)),"") -> 4.02 | H6: =IFERROR(INDEX(Monthly!$D$5:$D$109,MATCH(H$3,Monthly!$A$5:$A$109,0)),"") -> 4.39 | I6: =IFERROR(INDEX(Monthly!$D$5:$D$109,MATCH(I$3,Monthly!$A$5:$A$109,0)),"") -> 4.38 | ... M6: =IFERROR(INDEX(Monthly!$D$5:$D$109,MATCH(M$3,Monthly!$A$5:$A$109,0)),"") -> 0
A7: 1y Treasury yield (%) | B7: =IFERROR(INDEX(Monthly!$E$5:$E$109,MATCH(B$3,Monthly!$A$5:$A$109,0)),"") -> 1.549 | C7: =IFERROR(INDEX(Monthly!$E$5:$E$109,MATCH(C$3,Monthly!$A$5:$A$109,0)),"") -> 0.1764 | D7: =IFERROR(INDEX(Monthly!$E$5:$E$109,MATCH(D$3,Monthly!$A$5:$A$109,0)),"") -> 0.2991 | E7: =IFERROR(INDEX(Monthly!$E$5:$E$109,MATCH(E$3,Monthly!$A$5:$A$109,0)),"") -> 2.6514 | F7: =IFERROR(INDEX(Monthly!$E$5:$E$109,MATCH(F$3,Monthly!$A$5:$A$109,0)),"") -> 4.6819 | G7: =IFERROR(INDEX(Monthly!$E$5:$E$109,MATCH(G$3,Monthly!$A$5:$A$109,0)),"") -> 4.959 | H7: =IFERROR(INDEX(Monthly!$E$5:$E$109,MATCH(H$3,Monthly!$A$5:$A$109,0)),"") -> 4.2338 | I7: =IFERROR(INDEX(Monthly!$E$5:$E$109,MATCH(I$3,Monthly!$A$5:$A$109,0)),"") -> 4.062 | ... M7: =IFERROR(INDEX(Monthly!$E$5:$E$109,MATCH(M$3,Monthly!$A$5:$A$109,0)),"") -> 4.3652
A8: Fed funds effective (%) | B8: =IFERROR(INDEX(Monthly!$F$5:$F$109,MATCH(B$3,Monthly!$A$5:$A$109,0)),"") -> 1.55 | C8: =IFERROR(INDEX(Monthly!$F$5:$F$109,MATCH(C$3,Monthly!$A$5:$A$109,0)),"") -> 0.08 | D8: =IFERROR(INDEX(Monthly!$F$5:$F$109,MATCH(D$3,Monthly!$A$5:$A$109,0)),"") -> 0.08 | E8: =IFERROR(INDEX(Monthly!$F$5:$F$109,MATCH(E$3,Monthly!$A$5:$A$109,0)),"") -> 1.21 | F8: =IFERROR(INDEX(Monthly!$F$5:$F$109,MATCH(F$3,Monthly!$A$5:$A$109,0)),"") -> 4.1 | G8: =IFERROR(INDEX(Monthly!$F$5:$F$109,MATCH(G$3,Monthly!$A$5:$A$109,0)),"") -> 5.33 | H8: =IFERROR(INDEX(Monthly!$F$5:$F$109,MATCH(H$3,Monthly!$A$5:$A$109,0)),"") -> 4.48 | I8: =IFERROR(INDEX(Monthly!$F$5:$F$109,MATCH(I$3,Monthly!$A$5:$A$109,0)),"") -> 4.33 | ... M8: =IFERROR(INDEX(Monthly!$F$5:$F$109,MATCH(M$3,Monthly!$A$5:$A$109,0)),"") -> 3.75
A9: Curve 10y-1y (pp) | B9: =IFERROR(INDEX(Monthly!$G$5:$G$109,MATCH(B$3,Monthly!$A$5:$A$109,0)),"") -> 0.311 | C9: =IFERROR(INDEX(Monthly!$G$5:$G$109,MATCH(C$3,Monthly!$A$5:$A$109,0)),"") -> 0.5536 | D9: =IFERROR(INDEX(Monthly!$G$5:$G$109,MATCH(D$3,Monthly!$A$5:$A$109,0)),"") -> 1.1709 | E9: =IFERROR(INDEX(Monthly!$G$5:$G$109,MATCH(E$3,Monthly!$A$5:$A$109,0)),"") -> 0.4886 | F9: =IFERROR(INDEX(Monthly!$G$5:$G$109,MATCH(F$3,Monthly!$A$5:$A$109,0)),"") -> -1.0619 | G9: =IFERROR(INDEX(Monthly!$G$5:$G$109,MATCH(G$3,Monthly!$A$5:$A$109,0)),"") -> -0.939 | H9: =IFERROR(INDEX(Monthly!$G$5:$G$109,MATCH(H$3,Monthly!$A$5:$A$109,0)),"") -> 0.1562 | I9: =IFERROR(INDEX(Monthly!$G$5:$G$109,MATCH(I$3,Monthly!$A$5:$A$109,0)),"") -> 0.318 | ... M9: =IFERROR(INDEX(Monthly!$G$5:$G$109,MATCH(M$3,Monthly!$A$5:$A$109,0)),"")
A10: CPI inflation y/y | B10: =IFERROR(INDEX(Monthly!$I$5:$I$109,MATCH(B$3,Monthly!$A$5:$A$109,0)),"") -> 0.022851297 | C10: =IFERROR(INDEX(Monthly!$I$5:$I$109,MATCH(C$3,Monthly!$A$5:$A$109,0)),"") -> 0.0064573305 | D10: =IFERROR(INDEX(Monthly!$I$5:$I$109,MATCH(D$3,Monthly!$A$5:$A$109,0)),"") -> 0.070364029 | E10: =IFERROR(INDEX(Monthly!$I$5:$I$109,MATCH(E$3,Monthly!$A$5:$A$109,0)),"") -> 0.09059758 | F10: =IFERROR(INDEX(Monthly!$I$5:$I$109,MATCH(F$3,Monthly!$A$5:$A$109,0)),"") -> 0.064544013 | G10: =IFERROR(INDEX(Monthly!$I$5:$I$109,MATCH(G$3,Monthly!$A$5:$A$109,0)),"") -> 0.033521228 | H10: =IFERROR(INDEX(Monthly!$I$5:$I$109,MATCH(H$3,Monthly!$A$5:$A$109,0)),"") -> 0.028880572 | I10: =IFERROR(INDEX(Monthly!$I$5:$I$109,MATCH(I$3,Monthly!$A$5:$A$109,0)),"") -> 0.02669213 | ... M10: =IFERROR(INDEX(Monthly!$I$5:$I$109,MATCH(M$3,Monthly!$A$5:$A$109,0)),"")
A11: Unemployment rate (%) | B11: =IFERROR(INDEX(Monthly!$J$5:$J$109,MATCH(B$3,Monthly!$A$5:$A$109,0)),"") -> 3.6 | C11: =IFERROR(INDEX(Monthly!$J$5:$J$109,MATCH(C$3,Monthly!$A$5:$A$109,0)),"") -> 11 | D11: =IFERROR(INDEX(Monthly!$J$5:$J$109,MATCH(D$3,Monthly!$A$5:$A$109,0)),"") -> 3.9 | E11: =IFERROR(INDEX(Monthly!$J$5:$J$109,MATCH(E$3,Monthly!$A$5:$A$109,0)),"") -> 3.6 | F11: =IFERROR(INDEX(Monthly!$J$5:$J$109,MATCH(F$3,Monthly!$A$5:$A$109,0)),"") -> 3.5 | G11: =IFERROR(INDEX(Monthly!$J$5:$J$109,MATCH(G$3,Monthly!$A$5:$A$109,0)),"") -> 3.8 | H11: =IFERROR(INDEX(Monthly!$J$5:$J$109,MATCH(H$3,Monthly!$A$5:$A$109,0)),"") -> 4.1 | I11: =IFERROR(INDEX(Monthly!$J$5:$J$109,MATCH(I$3,Monthly!$A$5:$A$109,0)),"") -> 4.1 | ... M11: =IFERROR(INDEX(Monthly!$J$5:$J$109,MATCH(M$3,Monthly!$A$5:$A$109,0)),"") -> 4.2
A12: Sahm rule (pp) | B12: =IFERROR(INDEX(Monthly!$K$5:$K$109,MATCH(B$3,Monthly!$A$5:$A$109,0)),"") -> 0.03 | C12: =IFERROR(INDEX(Monthly!$K$5:$K$109,MATCH(C$3,Monthly!$A$5:$A$109,0)),"") -> 9.43 | D12: =IFERROR(INDEX(Monthly!$K$5:$K$109,MATCH(D$3,Monthly!$A$5:$A$109,0)),"") -> -0.27 | E12: =IFERROR(INDEX(Monthly!$K$5:$K$109,MATCH(E$3,Monthly!$A$5:$A$109,0)),"") -> -0.03 | F12: =IFERROR(INDEX(Monthly!$K$5:$K$109,MATCH(F$3,Monthly!$A$5:$A$109,0)),"") -> 0.03 | G12: =IFERROR(INDEX(Monthly!$K$5:$K$109,MATCH(G$3,Monthly!$A$5:$A$109,0)),"") -> 0.3 | H12: =IFERROR(INDEX(Monthly!$K$5:$K$109,MATCH(H$3,Monthly!$A$5:$A$109,0)),"") -> 0.4 | I12: =IFERROR(INDEX(Monthly!$K$5:$K$109,MATCH(I$3,Monthly!$A$5:$A$109,0)),"") -> 0.23 | ... M12: =IFERROR(INDEX(Monthly!$K$5:$K$109,MATCH(M$3,Monthly!$A$5:$A$109,0)),"") -> 0
A13: Nominal GDP y/y | B13: =IFERROR(INDEX(Monthly!$M$5:$M$109,MATCH(B$3,Monthly!$A$5:$A$109,0)),"") -> 0.048539844 | C13: =IFERROR(INDEX(Monthly!$M$5:$M$109,MATCH(C$3,Monthly!$A$5:$A$109,0)),"") -> -0.067279707 | D13: =IFERROR(INDEX(Monthly!$M$5:$M$109,MATCH(D$3,Monthly!$A$5:$A$109,0)),"") -> 0.12387423 | E13: =IFERROR(INDEX(Monthly!$M$5:$M$109,MATCH(E$3,Monthly!$A$5:$A$109,0)),"") -> 0.10285523 | F13: =IFERROR(INDEX(Monthly!$M$5:$M$109,MATCH(F$3,Monthly!$A$5:$A$109,0)),"") -> 0.078592921 | G13: =IFERROR(INDEX(Monthly!$M$5:$M$109,MATCH(G$3,Monthly!$A$5:$A$109,0)),"") -> 0.063127721 | H13: =IFERROR(INDEX(Monthly!$M$5:$M$109,MATCH(H$3,Monthly!$A$5:$A$109,0)),"") -> 0.051476611 | I13: =IFERROR(INDEX(Monthly!$M$5:$M$109,MATCH(I$3,Monthly!$A$5:$A$109,0)),"") -> 0.047795701 | ... M13: =IFERROR(INDEX(Monthly!$M$5:$M$109,MATCH(M$3,Monthly!$A$5:$A$109,0)),"")
A14: Federal debt (% GDP, qtr) | B14: =IFERROR(INDEX(Monthly!$N$5:$N$109,MATCH(B$3,Monthly!$A$5:$A$109,0)),"") -> 105.7819 | C14: =IFERROR(INDEX(Monthly!$N$5:$N$109,MATCH(C$3,Monthly!$A$5:$A$109,0)),"") -> 132.6629 | D14: =IFERROR(INDEX(Monthly!$N$5:$N$109,MATCH(D$3,Monthly!$A$5:$A$109,0)),"") -> 119.3588 | E14: =IFERROR(INDEX(Monthly!$N$5:$N$109,MATCH(E$3,Monthly!$A$5:$A$109,0)),"") -> 118.2021 | F14: =IFERROR(INDEX(Monthly!$N$5:$N$109,MATCH(F$3,Monthly!$A$5:$A$109,0)),"") -> 117.3668 | G14: =IFERROR(INDEX(Monthly!$N$5:$N$109,MATCH(G$3,Monthly!$A$5:$A$109,0)),"") -> 119.6194 | H14: =IFERROR(INDEX(Monthly!$N$5:$N$109,MATCH(H$3,Monthly!$A$5:$A$109,0)),"") -> 121.4363 | I14: =IFERROR(INDEX(Monthly!$N$5:$N$109,MATCH(I$3,Monthly!$A$5:$A$109,0)),"") -> 118.7817 | ... M14: =IFERROR(INDEX(Monthly!$N$5:$N$109,MATCH(M$3,Monthly!$A$5:$A$109,0)),"") -> 0
A15: Interest paid (% GDP) | B15: =IFERROR(INDEX(Monthly!$P$5:$P$109,MATCH(B$3,Monthly!$A$5:$A$109,0)),"") -> 0.02572541 | C15: =IFERROR(INDEX(Monthly!$P$5:$P$109,MATCH(C$3,Monthly!$A$5:$A$109,0)),"") -> 0.025790635 | D15: =IFERROR(INDEX(Monthly!$P$5:$P$109,MATCH(D$3,Monthly!$A$5:$A$109,0)),"") -> 0.024607031 | E15: =IFERROR(INDEX(Monthly!$P$5:$P$109,MATCH(E$3,Monthly!$A$5:$A$109,0)),"") -> 0.026403869 | F15: =IFERROR(INDEX(Monthly!$P$5:$P$109,MATCH(F$3,Monthly!$A$5:$A$109,0)),"") -> 0.030727736 | G15: =IFERROR(INDEX(Monthly!$P$5:$P$109,MATCH(G$3,Monthly!$A$5:$A$109,0)),"") -> 0.036073179 | H15: =IFERROR(INDEX(Monthly!$P$5:$P$109,MATCH(H$3,Monthly!$A$5:$A$109,0)),"") -> 0.038972986 | I15: =IFERROR(INDEX(Monthly!$P$5:$P$109,MATCH(I$3,Monthly!$A$5:$A$109,0)),"") -> 0.039083421 | ... M15: =IFERROR(INDEX(Monthly!$P$5:$P$109,MATCH(M$3,Monthly!$A$5:$A$109,0)),"")
A16: M2 y/y | B16: =IFERROR(INDEX(Monthly!$R$5:$R$109,MATCH(B$3,Monthly!$A$5:$A$109,0)),"") -> 0.066668983 | C16: =IFERROR(INDEX(Monthly!$R$5:$R$109,MATCH(C$3,Monthly!$A$5:$A$109,0)),"") -> 0.22847798 | D16: =IFERROR(INDEX(Monthly!$R$5:$R$109,MATCH(D$3,Monthly!$A$5:$A$109,0)),"") -> 0.12465872 | E16: =IFERROR(INDEX(Monthly!$R$5:$R$109,MATCH(E$3,Monthly!$A$5:$A$109,0)),"") -> 0.057359313 | F16: =IFERROR(INDEX(Monthly!$R$5:$R$109,MATCH(F$3,Monthly!$A$5:$A$109,0)),"") -> -0.0097475678 | G16: =IFERROR(INDEX(Monthly!$R$5:$R$109,MATCH(G$3,Monthly!$A$5:$A$109,0)),"") -> -0.024106287 | H16: =IFERROR(INDEX(Monthly!$R$5:$R$109,MATCH(H$3,Monthly!$A$5:$A$109,0)),"") -> 0.034056949 | I16: =IFERROR(INDEX(Monthly!$R$5:$R$109,MATCH(I$3,Monthly!$A$5:$A$109,0)),"") -> 0.041379736 | ... M16: =IFERROR(INDEX(Monthly!$R$5:$R$109,MATCH(M$3,Monthly!$A$5:$A$109,0)),"")
A17: Fed balance sheet ($trn) | B17: =IFERROR(INDEX(Monthly!$S$5:$S$109,MATCH(B$3,Monthly!$A$5:$A$109,0)),"") -> 4.116 | C17: =IFERROR(INDEX(Monthly!$S$5:$S$109,MATCH(C$3,Monthly!$A$5:$A$109,0)),"") -> 7.1278 | D17: =IFERROR(INDEX(Monthly!$S$5:$S$109,MATCH(D$3,Monthly!$A$5:$A$109,0)),"") -> 8.7239 | E17: =IFERROR(INDEX(Monthly!$S$5:$S$109,MATCH(E$3,Monthly!$A$5:$A$109,0)),"") -> 8.9227 | F17: =IFERROR(INDEX(Monthly!$S$5:$S$109,MATCH(F$3,Monthly!$A$5:$A$109,0)),"") -> 8.5704 | G17: =IFERROR(INDEX(Monthly!$S$5:$S$109,MATCH(G$3,Monthly!$A$5:$A$109,0)),"") -> 7.7284 | H17: =IFERROR(INDEX(Monthly!$S$5:$S$109,MATCH(H$3,Monthly!$A$5:$A$109,0)),"") -> 6.8922 | I17: =IFERROR(INDEX(Monthly!$S$5:$S$109,MATCH(I$3,Monthly!$A$5:$A$109,0)),"") -> 6.6733 | ... M17: =IFERROR(INDEX(Monthly!$S$5:$S$109,MATCH(M$3,Monthly!$A$5:$A$109,0)),"") -> 6.743
A18: Industrial production y/y | B18: =IFERROR(INDEX(Monthly!$U$5:$U$109,MATCH(B$3,Monthly!$A$5:$A$109,0)),"") -> -0.022991807 | C18: =IFERROR(INDEX(Monthly!$U$5:$U$109,MATCH(C$3,Monthly!$A$5:$A$109,0)),"") -> -0.10586065 | D18: =IFERROR(INDEX(Monthly!$U$5:$U$109,MATCH(D$3,Monthly!$A$5:$A$109,0)),"") -> 0.022463731 | E18: =IFERROR(INDEX(Monthly!$U$5:$U$109,MATCH(E$3,Monthly!$A$5:$A$109,0)),"") -> 0.012217594 | F18: =IFERROR(INDEX(Monthly!$U$5:$U$109,MATCH(F$3,Monthly!$A$5:$A$109,0)),"") -> -0.0080160998 | G18: =IFERROR(INDEX(Monthly!$U$5:$U$109,MATCH(G$3,Monthly!$A$5:$A$109,0)),"") -> 0.0083865911 | H18: =IFERROR(INDEX(Monthly!$U$5:$U$109,MATCH(H$3,Monthly!$A$5:$A$109,0)),"") -> -0.0027414662 | I18: =IFERROR(INDEX(Monthly!$U$5:$U$109,MATCH(I$3,Monthly!$A$5:$A$109,0)),"") -> 0.0057932087 | ... M18: =IFERROR(INDEX(Monthly!$U$5:$U$109,MATCH(M$3,Monthly!$A$5:$A$109,0)),"")
A19: Retail sales y/y | B19: =IFERROR(INDEX(Monthly!$W$5:$W$109,MATCH(B$3,Monthly!$A$5:$A$109,0)),"") -> 0.053880762 | C19: =IFERROR(INDEX(Monthly!$W$5:$W$109,MATCH(C$3,Monthly!$A$5:$A$109,0)),"") -> 0.026334784 | D19: =IFERROR(INDEX(Monthly!$W$5:$W$109,MATCH(D$3,Monthly!$A$5:$A$109,0)),"") -> 0.15259296 | E19: =IFERROR(INDEX(Monthly!$W$5:$W$109,MATCH(E$3,Monthly!$A$5:$A$109,0)),"") -> 0.091992787 | F19: =IFERROR(INDEX(Monthly!$W$5:$W$109,MATCH(F$3,Monthly!$A$5:$A$109,0)),"") -> 0.042736926 | G19: =IFERROR(INDEX(Monthly!$W$5:$W$109,MATCH(G$3,Monthly!$A$5:$A$109,0)),"") -> 0.028779664 | H19: =IFERROR(INDEX(Monthly!$W$5:$W$109,MATCH(H$3,Monthly!$A$5:$A$109,0)),"") -> 0.037229951 | I19: =IFERROR(INDEX(Monthly!$W$5:$W$109,MATCH(I$3,Monthly!$A$5:$A$109,0)),"") -> 0.038800973 | ... M19: =IFERROR(INDEX(Monthly!$W$5:$W$109,MATCH(M$3,Monthly!$A$5:$A$109,0)),"")
A20: Nominal PCE y/y | B20: =IFERROR(INDEX(Monthly!$Y$5:$Y$109,MATCH(B$3,Monthly!$A$5:$A$109,0)),"") -> 0.051467449 | C20: =IFERROR(INDEX(Monthly!$Y$5:$Y$109,MATCH(C$3,Monthly!$A$5:$A$109,0)),"") -> -0.024950204 | D20: =IFERROR(INDEX(Monthly!$Y$5:$Y$109,MATCH(D$3,Monthly!$A$5:$A$109,0)),"") -> 0.13879369 | E20: =IFERROR(INDEX(Monthly!$Y$5:$Y$109,MATCH(E$3,Monthly!$A$5:$A$109,0)),"") -> 0.095709122 | F20: =IFERROR(INDEX(Monthly!$Y$5:$Y$109,MATCH(F$3,Monthly!$A$5:$A$109,0)),"") -> 0.071442959 | G20: =IFERROR(INDEX(Monthly!$Y$5:$Y$109,MATCH(G$3,Monthly!$A$5:$A$109,0)),"") -> 0.062366257 | H20: =IFERROR(INDEX(Monthly!$Y$5:$Y$109,MATCH(H$3,Monthly!$A$5:$A$109,0)),"") -> 0.064836309 | I20: =IFERROR(INDEX(Monthly!$Y$5:$Y$109,MATCH(I$3,Monthly!$A$5:$A$109,0)),"") -> 0.051786825 | ... M20: =IFERROR(INDEX(Monthly!$Y$5:$Y$109,MATCH(M$3,Monthly!$A$5:$A$109,0)),"")
A21: Real disposable income y/y | B21: =IFERROR(INDEX(Monthly!$AA$5:$AA$109,MATCH(B$3,Monthly!$A$5:$A$109,0)),"") -> 0.011433915 | C21: =IFERROR(INDEX(Monthly!$AA$5:$AA$109,MATCH(C$3,Monthly!$A$5:$A$109,0)),"") -> 0.095623341 | D21: =IFERROR(INDEX(Monthly!$AA$5:$AA$109,MATCH(D$3,Monthly!$A$5:$A$109,0)),"") -> 0.01520945 | E21: =IFERROR(INDEX(Monthly!$AA$5:$AA$109,MATCH(E$3,Monthly!$A$5:$A$109,0)),"") -> -0.045001871 | F21: =IFERROR(INDEX(Monthly!$AA$5:$AA$109,MATCH(F$3,Monthly!$A$5:$A$109,0)),"") -> -0.0033999916 | G21: =IFERROR(INDEX(Monthly!$AA$5:$AA$109,MATCH(G$3,Monthly!$A$5:$A$109,0)),"") -> 0.060209156 | H21: =IFERROR(INDEX(Monthly!$AA$5:$AA$109,MATCH(H$3,Monthly!$A$5:$A$109,0)),"") -> 0.021291232 | I21: =IFERROR(INDEX(Monthly!$AA$5:$AA$109,MATCH(I$3,Monthly!$A$5:$A$109,0)),"") -> 0.012244121 | ... M21: =IFERROR(INDEX(Monthly!$AA$5:$AA$109,MATCH(M$3,Monthly!$A$5:$A$109,0)),"")
A22: House prices y/y | B22: =IFERROR(INDEX(Monthly!$AC$5:$AC$109,MATCH(B$3,Monthly!$A$5:$A$109,0)),"") -> 0.03679201 | C22: =IFERROR(INDEX(Monthly!$AC$5:$AC$109,MATCH(C$3,Monthly!$A$5:$A$109,0)),"") -> 0.043795239 | D22: =IFERROR(INDEX(Monthly!$AC$5:$AC$109,MATCH(D$3,Monthly!$A$5:$A$109,0)),"") -> 0.18864059 | E22: =IFERROR(INDEX(Monthly!$AC$5:$AC$109,MATCH(E$3,Monthly!$A$5:$A$109,0)),"") -> 0.17978561 | F22: =IFERROR(INDEX(Monthly!$AC$5:$AC$109,MATCH(F$3,Monthly!$A$5:$A$109,0)),"") -> 0.056274865 | G22: =IFERROR(INDEX(Monthly!$AC$5:$AC$109,MATCH(G$3,Monthly!$A$5:$A$109,0)),"") -> 0.056662395 | H22: =IFERROR(INDEX(Monthly!$AC$5:$AC$109,MATCH(H$3,Monthly!$A$5:$A$109,0)),"") -> 0.039971047 | I22: =IFERROR(INDEX(Monthly!$AC$5:$AC$109,MATCH(I$3,Monthly!$A$5:$A$109,0)),"") -> 0.019393954 | ... M22: =IFERROR(INDEX(Monthly!$AC$5:$AC$109,MATCH(M$3,Monthly!$A$5:$A$109,0)),"")
A23: Brent ($/bbl, monthly avg) | B23: =IFERROR(INDEX(Monthly!$AD$5:$AD$109,MATCH(B$3,Monthly!$A$5:$A$109,0)),"") -> 67.31 | C23: =IFERROR(INDEX(Monthly!$AD$5:$AD$109,MATCH(C$3,Monthly!$A$5:$A$109,0)),"") -> 40.27 | D23: =IFERROR(INDEX(Monthly!$AD$5:$AD$109,MATCH(D$3,Monthly!$A$5:$A$109,0)),"") -> 74.17 | E23: =IFERROR(INDEX(Monthly!$AD$5:$AD$109,MATCH(E$3,Monthly!$A$5:$A$109,0)),"") -> 122.71 | F23: =IFERROR(INDEX(Monthly!$AD$5:$AD$109,MATCH(F$3,Monthly!$A$5:$A$109,0)),"") -> 80.92 | G23: =IFERROR(INDEX(Monthly!$AD$5:$AD$109,MATCH(G$3,Monthly!$A$5:$A$109,0)),"") -> 77.63 | H23: =IFERROR(INDEX(Monthly!$AD$5:$AD$109,MATCH(H$3,Monthly!$A$5:$A$109,0)),"") -> 73.86 | I23: =IFERROR(INDEX(Monthly!$AD$5:$AD$109,MATCH(I$3,Monthly!$A$5:$A$109,0)),"") -> 71.44 | ... M23: =IFERROR(INDEX(Monthly!$AD$5:$AD$109,MATCH(M$3,Monthly!$A$5:$A$109,0)),"") -> 114.16
A24: Gold ($/oz, monthly) | B24: =IFERROR(INDEX(Monthly!$AF$5:$AF$109,MATCH(B$3,Monthly!$A$5:$A$109,0)),"") -> 1479 | C24: =IFERROR(INDEX(Monthly!$AF$5:$AF$109,MATCH(C$3,Monthly!$A$5:$A$109,0)),"") -> 1732 | D24: =IFERROR(INDEX(Monthly!$AF$5:$AF$109,MATCH(D$3,Monthly!$A$5:$A$109,0)),"") -> 1790 | E24: =IFERROR(INDEX(Monthly!$AF$5:$AF$109,MATCH(E$3,Monthly!$A$5:$A$109,0)),"") -> 1837 | F24: =IFERROR(INDEX(Monthly!$AF$5:$AF$109,MATCH(F$3,Monthly!$A$5:$A$109,0)),"") -> 1798 | G24: =IFERROR(INDEX(Monthly!$AF$5:$AF$109,MATCH(G$3,Monthly!$A$5:$A$109,0)),"") -> 2026 | H24: =IFERROR(INDEX(Monthly!$AF$5:$AF$109,MATCH(H$3,Monthly!$A$5:$A$109,0)),"") -> 2648 | I24: =IFERROR(INDEX(Monthly!$AF$5:$AF$109,MATCH(I$3,Monthly!$A$5:$A$109,0)),"") -> 3353 | ... M24: =IFERROR(INDEX(Monthly!$AF$5:$AF$109,MATCH(M$3,Monthly!$A$5:$A$109,0)),"") -> 4319
A25: VIX (monthly close) | B25: =IFERROR(INDEX(Monthly!$AH$5:$AH$109,MATCH(B$3,Monthly!$A$5:$A$109,0)),"") -> 13.78 | C25: =IFERROR(INDEX(Monthly!$AH$5:$AH$109,MATCH(C$3,Monthly!$A$5:$A$109,0)),"") -> 30.43 | D25: =IFERROR(INDEX(Monthly!$AH$5:$AH$109,MATCH(D$3,Monthly!$A$5:$A$109,0)),"") -> 17.22 | E25: =IFERROR(INDEX(Monthly!$AH$5:$AH$109,MATCH(E$3,Monthly!$A$5:$A$109,0)),"") -> 28.71 | F25: =IFERROR(INDEX(Monthly!$AH$5:$AH$109,MATCH(F$3,Monthly!$A$5:$A$109,0)),"") -> 21.67 | G25: =IFERROR(INDEX(Monthly!$AH$5:$AH$109,MATCH(G$3,Monthly!$A$5:$A$109,0)),"") -> 12.45 | H25: =IFERROR(INDEX(Monthly!$AH$5:$AH$109,MATCH(H$3,Monthly!$A$5:$A$109,0)),"") -> 17.35 | I25: =IFERROR(INDEX(Monthly!$AH$5:$AH$109,MATCH(I$3,Monthly!$A$5:$A$109,0)),"") -> 16.73 | ... M25: =IFERROR(INDEX(Monthly!$AH$5:$AH$109,MATCH(M$3,Monthly!$A$5:$A$109,0)),"") -> 14.21
A26: EUR/USD (monthly avg) | B26: =IFERROR(INDEX(Monthly!$AI$5:$AI$109,MATCH(B$3,Monthly!$A$5:$A$109,0)),"") -> 1.1114 | C26: =IFERROR(INDEX(Monthly!$AI$5:$AI$109,MATCH(C$3,Monthly!$A$5:$A$109,0)),"") -> 1.1259 | D26: =IFERROR(INDEX(Monthly!$AI$5:$AI$109,MATCH(D$3,Monthly!$A$5:$A$109,0)),"") -> 1.1301 | E26: =IFERROR(INDEX(Monthly!$AI$5:$AI$109,MATCH(E$3,Monthly!$A$5:$A$109,0)),"") -> 1.0567 | F26: =IFERROR(INDEX(Monthly!$AI$5:$AI$109,MATCH(F$3,Monthly!$A$5:$A$109,0)),"") -> 1.0591 | G26: =IFERROR(INDEX(Monthly!$AI$5:$AI$109,MATCH(G$3,Monthly!$A$5:$A$109,0)),"") -> 1.0909 | H26: =IFERROR(INDEX(Monthly!$AI$5:$AI$109,MATCH(H$3,Monthly!$A$5:$A$109,0)),"") -> 1.0472 | I26: =IFERROR(INDEX(Monthly!$AI$5:$AI$109,MATCH(I$3,Monthly!$A$5:$A$109,0)),"") -> 1.1534 | ... M26: =IFERROR(INDEX(Monthly!$AI$5:$AI$109,MATCH(M$3,Monthly!$A$5:$A$109,0)),"") -> 1.1505

Sheet Sources
A1: Built | B1: 2026-10-10 15:20 UTC
A2: Why mirrors | B2: This environment cannot reach fred.stlouisfed.org, BLS, BEA, Treasury or Yahoo directly (network policy). Data were taken from GitHub-hosted mirrors that pull the official series automatically.
A3: FRED mirror | B3: github.com/njuettner/fed - daily GitHub Action calling the FRED API (series IDs in each header comment). Pulled 9-10 Oct 2026. Its 2y-yield, CPI-change and housing files stopped updating in 2024 and were not used beyond that.
A4: Shiller S&P 500 | B4: github.com/datasets/s-and-p-500 (data/data.csv), monthly average price; earnings/dividend columns stop in mid-2023 and were not used.
A5: CPI | B5: FRED CPIAUCNS via the FRED mirror (cpi_raw), cross-checked with github.com/datasets/cpi-us.
A6: Gold, Brent, VIX, house prices | B6: github.com/datasets/gold-prices, oil-prices, finance-vix, house-prices-us.
A7: Derived columns | B7: All y/y, curve and ratio columns are live formulas on the Monthly sheet; change an input and they recalculate.
A8: Data prep | B8: Daily series (DGS1, DEXUSEU, DCOILWTICO, RESPPANWW) were averaged to monthly before writing. Quarterly series are held across the quarter.
A9: Not available | B9: Core CPI, core PCE, federal deficit, HY/IG spreads, 2y yield after Feb 2024, TIPS real yields, payrolls, mortgage rates, S&P earnings/margins/P-E. Point values for these are on the Anchors sheet, with provenance.
A10: Caveat | B10: Anchor values marked "memory" are approximate and unverified. Feed values are as published by the mirrors on the pull date and are subject to official revisions.
